{
  "accessDeniedPage": {
    "body": "दुर्भाग्यवश, आपके देश से की गई गतिविधि वर्तमान में अनुमत नहीं है।",
    "title": "प्रवेश अस्वीकृत"
  },
  "addressWhitelistPage": {
    "addAddress": "निम्नलिखित को एक स्वीकृत निकासी पते के रूप में जोड़ें:",
    "goToAccount": "अपने <1>{{selectedIntegrationName}} खाते</1> पर जाएं",
    "network": "नेटवर्क",
    "preview": "पुनः इस स्थानांतरण की पूर्वावलोकन और आरंभ करने के लिए नीचे क्लिक करें",
    "title": "इस गंतव्य को स्वीकृत सूची में जोड़ें",
    "token": "टोकन"
  },
  "authCodeInput": {
    "code": "6 अंक कोड"
  },
  "binanceConnectAmountInput": {
    "switchFiatCrypto": "फिएट/क्रिप्टो स्विच करें"
  },
  "binanceConnectOAuthPage": {
    "amountMustBeWithin": "राशि {{minFiat}} {{selectedFiat}} - {{maxFiat}} {{selectedFiat}} के भीतर होनी चाहिए",
    "amountMustBeWithinErrorMessage": "राशि USD $21 - $15,000 के भीतर होनी चाहिए",
    "buyCrypto": "Binance Connect का उपयोग करके क्रिप्टो खरीदें",
    "closeButton": "बंद करें",
    "continueTo": "{{selectedIntegrationName}} पर जारी रखें",
    "enterAmount": "स्थानांतरण राशि दर्ज करें",
    "notSupported": "{{selectedIntegrationName}} अनुरोधित टोकन और/या नेटवर्क के लिए स्थानांतरण का समर्थन नहीं करता है।",
    "receiveAmountInput": {
      "networkName": "{{networkName}} पर"
    },
    "selectAnotherAccount": "अन्य खाता चुनें",
    "selectAnotherExchange": "कृपया जमा करने के लिए अन्य एक्सचेंज या वॉलेट को चुनें।",
    "selectAsset": "स्थानांतरण के लिए संपत्ति चुनें",
    "selectCurrency": "एक मुद्रा का चयन करें",
    "selectNetwork": "स्थानांतरण नेटवर्क चुनें",
    "youPay": "आप भुगतान करेंगे",
    "youReceive": "आप प्राप्त करेंगे"
  },
  "binanceMfaPage": {
    "add2fa": "कृपया Binance में आवश्यक टू-फैक्टर ऑथेंटिकेशन (2FA) विधियाँ जोड़ें",
    "chooseAnotherAccount": "दूसरा खाता चुनें",
    "description": "आपको अपने <1>Binance</1> खाते में दोनों ईमेल और ऑथेंटिकेटर ऐप को 2FA विधियों के रूप में सेट अप करना होगा।",
    "ensureConfigured": "सुनिश्चित करें कि सुरक्षा के लिए आपके ईमेल और ऑथेंटिकेटर ऐप दोनों 2FA के लिए सेट किए गए हैं",
    "goToSettings": "अपने <1>Binance</1> सुरक्षा सेटिंग्स पर जाने के लिए नीचे क्लिक करें",
    "mayNeedReAuthApp": "कृपया ध्यान दें: जब आप <2>एप्लिकेशन</2> पर लौटते हैं तो आपको इस स्थानांतरण को शुरू करने के लिए अपने Binance खाते में पुनः प्रमाणीकरण की आवश्यकता हो सकती है।",
    "mayNeedReAuthClient": "कृपया ध्यान दें: जब आप <2>{{clientName}}</2> पर वापस लौटते हैं, तो आपको इस स्थानांतरण को शुरू करने के लिए अपने Binance खाते में पुनः प्रमाणीकरण की आवश्यकता हो सकती है।",
    "openBinance": "Binance खोलें",
    "returnToApp": "इस स्थानांतरण को पुनः प्रयास करने के लिए <1>एप्लिकेशन</1> पर लौटें",
    "returnToClient": "इस स्थानांतरण को पुनः प्रयास करने के लिए <1>{{clientName}}</1> पर लौटें",
    "title": "अपने Binance खाते से निकासी को सक्षम करें"
  },
  "binanceResetPasswordPage": {
    "goToBinance": "Binance.com पर जाएं",
    "securityNote": "नोट: आपकी सुरक्षा के लिए, पासवर्ड बदलने के 24 घंटे बाद तक क्रिप्टो निकासी अक्षम रहती है।",
    "steps": {
      "completeProcess": "अपना पासवर्ड रीसेट करने की प्रक्रिया पूरी करें।",
      "enterEmail": "अपना ईमेल या फोन नंबर दर्ज करें, और \"पासवर्ड भूल गए?\" पर क्लिक करें।",
      "goToBinance": "<1>Binance.com पर जाएं</1> चुनें और आपको Binance लॉगिन स्क्रीन पर ले जाया जाएगा।",
      "returnToLogin": "अपने नए पासवर्ड के साथ लॉगिन करने के लिए यहीं वापस आएं।"
    },
    "title": "पासवर्ड रीसेट करें"
  },
  "bindFacePage": {
    "completedButton": "मैंने इसे अपने फ़ोन पर पूरा कर लिया है",
    "linkText": "यदि आप QR कोड स्कैन करने में असमर्थ हैं, तो कृपया इस <2><0>लिंक</0></2> का अनुसरण करें।",
    "qrCode": "QR कोड",
    "return": "जारी रखने के लिए इस स्क्रीन पर लौटें।",
    "title": "Binance ऐप खोलें और नीचे दिए गए QR कोड को स्कैन करें"
  },
  "bindMfaList": {
    "authApp": "अथेंटिकेटर ऐप",
    "email": "ईमेल",
    "enabled": "सक्रिय",
    "error": "MFA को जोड़ने में विफल",
    "notEnabled": "सक्रिय नहीं है"
  },
  "browserContent": {
    "openButtom": "{{integrationName}} खोलें"
  },
  "catalogCell": {
    "select": "{{integrationName}}, {{badge}} चुनें"
  },
  "catalogList": {
    "badges": {
      "api": "एपीआई",
      "installed": "इंस्टॉल किया गया",
      "linked": "पहले से जुड़ा हुआ"
    },
    "noResults": "माफ़ कीजिए, हमें कोई परिणाम नहीं मिला",
    "paymentTitle": "भुगतान खाता चुनें",
    "prodOnly": "केवल उत्पादन के लिए",
    "search": "खोज",
    "title": "लिंक करने के लिए खाता चुनें",
    "title40": "अपना खाता चुनें"
  },
  "catalogTile": {
    "select": "{{integrationName}}, {{badge}} चुनें"
  },
  "categories": {
    "brokerage": "दलाली",
    "deFiWallet": "वॉलेट्स",
    "deFiWalletFull": "स्व-उपचारित क्रिप्टो वॉलेट्स",
    "exchange": "एक्सचेंज",
    "exchangeFull": "केंद्रीकृत क्रिप्टो एक्सचेंज",
    "nftMarketplace": "NFT मार्केटप्लेस",
    "popular": "लोकप्रिय"
  },
  "chainSwitch": {
    "monitoringApproval": "मंजूरी की प्रतीक्षा में...",
    "networkChangeDeclined": "नेटवर्क परिवर्तन अस्वीकार किया गया",
    "networkChangeDeclinedBody": "आपने अपने वॉलेट में नेटवर्क बदलने का अनुरोध अस्वीकार कर दिया है",
    "resendNetworkSwitch": "नेटवर्क स्विच अनुरोध फिर से भेजें",
    "stayOnNetwork": "{{networkName}} पर बने रहें",
    "switchingNetwork": "नेटवर्क बदल रहा है",
    "tryAgain": "पुनः प्रयास करें"
  },
  "challengePage": {
    "changeQuestion": "प्रश्न बदलें",
    "codeHeader": "अपना सत्यापन कोड दर्ज करें",
    "questionHeader": "अपने सुरक्षा प्रश्न का उत्तर दें",
    "securityQuestionInputTitle": "सुरक्षा प्रश्न",
    "title": "सत्यापन",
    "verificationCodeInputTitle": "सत्यापन कोड"
  },
  "chooseAccountPage": {
    "linkToApp": "आप अपने खातों में से किसे <1></1> इस एप्लिकेशन से जोड़ना चाहेंगे",
    "linkToClient": "आप अपने किस खाते को <1></1> {{clientName}} से जोड़ना चाहेंगे",
    "title": "उप-खातों का चयन करें"
  },
  "common": {
    "availableForTransfer": "उपलब्ध",
    "cancel": "रद्द करें",
    "closeCap": "बंद करें",
    "codeNotCorrent": "प्रदान किया गया कोड सही नहीं है।",
    "continueCap": "जारी रखें",
    "doneCap": "हो गया",
    "failedToLoadTrasferError": "स्थानांतरण के बारे में जानकारी लोड करने में विफल",
    "genericConnectErrorMessage": "आपके इंटीग्रेशन से कनेक्ट होने में विफल",
    "maxCap": "अधिकतम",
    "mesh": "Mesh",
    "notFound": "नहीं मिला",
    "searchCap": "खोजें",
    "securedBy": "द्वारा सुरक्षित",
    "somethingWentWrong": "कुछ गलत हो गया...",
    "submitCap": "जमा करें",
    "successTitle": "सफलता!",
    "termsOfUse": "जारी रखकर आप <2>प्रयोग की शर्तें</2> स्वीकार करते हैं",
    "tryAgain": "पुनः प्रयास करें"
  },
  "commonContent": {
    "connecting": "कनेक्ट हो रहा है...",
    "description": "{{integrationName}} के साथ सुरक्षित कनेक्शन स्थापित करेगा।",
    "monitoring": "मंजूरी की प्रतीक्षा में...",
    "resend": "कनेक्शन अनुरोध पुनः भेजें",
    "title": "अपने वॉलेट में कनेक्शन<1></1> अनुरोध को स्वीकृति दें",
    "title40": "अपने<1></1> {{walletName}} ऐप में कनेक्शन अनुरोध को स्वीकृति दें।",
    "takingLongerTitle": "अब भी वहां हैं?… अपना बटुआ देखें और जारी रखने के लिए अनुरोध को स्वीकृति दें।"
  },
  "connectExternalPageScreen": {
    "connectedTitle": "अपने {{selectedIntegrationName}} को कनेक्ट करने के लिए अपने डेस्कटॉप पर निर्देशों का पालन करें",
    "failedBody": "आपके {{integrationName}} से कनेक्शन स्थापित करने में असमर्थ। कृपया जांचें कि आपका पता और नेटवर्क आइडी सही हैं और पुनः प्रयास करें।",
    "failedTitle": "कनेक्शन असफल रहा",
    "notConnectedStep1": "1. इस लिंक को <1>डेस्कटॉप</1> उपकरण पर खोलें",
    "notConnectedStep2": "2. अपने वॉलेट को सुरक्षित तरीके से कनेक्ट करने के लिए यह कोड दर्ज करें",
    "notConnectedTitle": "अपने {{selectedIntegrationName}} को कनेक्ट करने के लिए डेस्कटॉप डिवाइस का उपयोग करें"
  },
  "connectionDeclinedPage": {
    "connectAnother": "अन्य खाता कनेक्ट करें"
  },
  "connectionFailedPage": {
    "defaultError": "एक त्रुटि उत्पन्न हुई है।",
    "directMobileFlowError": "सत्र समाप्त हो गया। कृपया अपने TAO चेकआउट पृष्ठ पर लौटें और फिर से प्रयास करें।"
  },
  "connectionUnavailablePage": {
    "connectAnother": "अन्य वॉलेट कनेक्ट करें",
    "installApp": "मोबाइल ऐप इंस्टॉल करें"
  },
  "countryBlockedPage": {
    "body": "यह सुविधा अभी आपके<1></1> देश में समर्थित नहीं है। कृपया जल्द ही फिर से जांचें एक<3></3> सुव्यवस्थित जमा अनुभव के लिए।",
    "comingSoon": "जल्द आ रहा है"
  },
  "currencyBox": {
    "changeCurrency": "मुद्रा बदलें"
  },
  "deFiWalletDeclinedConnectionPage": {
    "connectionDeclinedBody": "आपने अपने वॉलेट को कनेक्ट करने के अनुरोध को अस्वीकार कर दिया है, या एक पिछला अनुरोध अभी भी सक्रिय है।",
    "connectionDeclinedTitle": "कनेक्शन अस्वीकृत",
    "networkDeclinedBody": "आपने अपने वॉलेट में नेटवर्क बदलने के अनुरोध को अस्वीकार कर दिया है।",
    "networkDeclinedTitle": "नेटवर्क परिवर्तन अस्वीकृत"
  },
  "deFiWalletDrawerContent": {
    "actionButton": "{{selectedIntegrationName}} के साथ कनेक्ट करें"
  },
  "deFiWalletInitialPage": {
    "continue": "{{walletName}} पर जारी रखें",
    "previewButton": "जुड़ें",
    "previewTitle": "खाता जोड़ें",
    "subtitle": "{{walletName}} खोलने के लिए नीचे क्लिक करें। फिर अपने भुगतान का पूर्वावलोकन करने के लिए कनेक्शन अनुरोध को स्वीकृत करें।",
    "title": "अपने वॉलेट को जोड़ें"
  },
  "defiWalletQrPage": {
    "declinedBody": "आपने अपनी वॉलेट से कनेक्ट करने के अनुरोध को अस्वीकृत कर दिया है, या एक पिछला अनुरोध अभी भी सक्रिय है।",
    "declinedTitle": "कनेक्शन अस्वीकृत",
    "description": "{{selectedIntegrationName}} खोलें और<3></3>क्यूआर कोड को स्कैन करें",
    "qrCodeLabel": "कनेक्शन स्थापित करने के लिए क्यूआर कोड को आपके मोबाइल डिवाइस पर स्कैन किया जा सकता है",
    "title": "{{selectedIntegrationName}} के साथ जुड़े"
  },
  "defiWalletSelectNetworkPage": {
    "declinedBody": "आपने अपने वॉलेट में नेटवर्क बदलने के अनुरोध को अस्वीकार कर दिया है।",
    "declineTitle": "नेटवर्क परिवर्तन अस्वीकृत",
    "monitoringApproval": "मंजूरी की प्रतीक्षा में...",
    "selectNetwork": "नेटवर्क चुनें",
    "title": "नेटवर्क्स बदल रहे हैं",
    "whichNetwork": "आप अपने <1>{{selectedIntegrationName}}</1> वॉलेट<4></4> में किस नेटवर्क को लिंक करना चाहेंगे?"
  },
  "defiWalletUnavaialbleConnectionPage": {
    "body": "{{integrationName}} इस डिवाइस पर इंस्टॉल नहीं है। कृपया {{integrationName}} ऐप इंस्टॉल करें, या एक अन्य वॉलेट कनेक्ट करें।",
    "title": "कनेक्शन उपलब्ध नहीं है"
  },
  "deFiWalletConnectionUnavailablePage": {
    "body": "Please check your wallet and approve the connection request.",
    "title": "We didn’t get a response in time",
    "chooseDifferentAccount": "Choose a different account"
  },
  "deFiWalletConnectionDeclinedPage": {
    "body": "It looks like you denied the connection request, or a previous request is still active. If that was a mistake, try again.",
    "title": "Oops!",
    "chooseDifferentAccount": "Choose a different account"
  },
  "deviceConfirmationScreenPage": {
    "awaitingConfirmation": "मोबाइल ऐप से पुष्टि की प्रतीक्षा की जा रही है",
    "clickOpenApp": "नीचे <1> {{integrationName}} ऐप खोलें</1> पर क्लिक करें",
    "confirmInApp": "अपने {{integrationName}} मोबाइल ऐप में पुष्टि करें कि यह वास्तव में आप लॉग इन करने की कोशिश कर रहे हैं।",
    "confirmPrompt": "यह आप हैं इसकी पुष्टि के लिए संकेत को स्वीकृति दें",
    "openApp": "{{integrationName}} ऐप खोलें",
    "openAppOnPhone": "अपने फ़ोन पर {{integrationName}} ऐप खोलें",
    "returnHere": "जारी रखने के लिए यहाँ लौटें",
    "sendNewRequest": "एक नई अनुरोध भेजें",
    "title": "सत्यापन",
    "tryAnotherWay": "दूसरे तरीके से प्रयास करें",
    "verified": "मैंने अपने ऐप पर सत्यापित कर दिया है",
    "verifyLoggedIn": "सुनिश्चित करें कि आप एक नए डिवाइस से लॉग इन कर रहे हैं"
  },
  "doneExternalVerifyScreen": {
    "body": "आपने सफलतापूर्वक अपने <2>{{selectedIntegrationName}}</2> वॉलेट की संपत्ति की पुष्टि की है।",
    "returnAction": "{{clientName}} पर लौटें"
  },
  "donePage": {
    "continueToDeposit": "जमा जारी रखें",
    "continueToPayment": "भुगतान जारी रखें",
    "continueToPurchase": "खरीद जारी रखें",
    "continueToTransfer": "स्थानांतरण जारी रखें",
    "done": "हो गया",
    "linkAnother": "अन्य खाता जोड़ें",
    "linkedToClient": "आपने<1></1><2>{{integrationName}}</2> को सफलतापूर्वक <5>{{clientName}}</5> से जोड़ दिया है।",
    "linkedToThisApp": "आपने सफलतापूर्वक<1></1><2>{{integrationName}}</2> को <5>इस एप्लिकेशन</5> से जोड़ दिया है।"
  },
  "doneTransferDetails": {
    "awaitinApprovalLabel": "यह स्थानांतरण तब तक शुरू नहीं होगा जब तक इसे {{selectedIntegrationName}} में स्वीकृत नहीं किया जाता।",
    "defaultTitle": "लेन-देन पूरा हुआ",
    "depositTitle": "जमा पूरा हुआ",
    "onrampTitle": "खरीद पूरी हुई",
    "paymentTitle": "भुगतान पूरा हुआ",
    "steps": {
      "approvedFromCeFiToClient": "आपने {{selectedIntegrationName}} से {{clientName}} तक स्थानांतरण को स्वीकृति दी है।",
      "approvedFromCeFiToDestination": "आपने {{selectedIntegrationName}} से गंतव्य तक स्थानांतरण को स्वीकृति दी है।",
      "approvedFromDeFi": "आपने {{selectedIntegrationName}} पर स्थानांतरण को स्वीकृति दी है।",
      "conversion": "<1>{{amount}}</1> को <4>{{currency}}</4> में रूपांतरित किया जा रहा है।",
      "deposit": "{{paymentMethod}} से {{selectedIntegrationName}} तक <1>{{amount}}</1> का जमा।",
      "purchase": "{{selectedIntegrationName}} में <1>{{amount}}</1> मूल्य का {{symbol}} की खरीद।",
      "requestToTransferPaymentSmartToAddress": "{{selectedIntegrationName}} से रिले अनुबंध {{shortSmartContractsAddress}} के माध्यम से <1>{{transferPreviewAmount}}</1> के स्थानांतरण का अनुरोध।",
      "requestToTransferPaymentSmartToClient": "{{selectedIntegrationName}} से {{clientName}} को रिले अनुबंध {{shortSmartContractsAddress}} के माध्यम से <1>{{transferPreviewAmount}}</1> के स्थानांतरण का अनुरोध।",
      "requestToTransferPaymentToAddress": "{{selectedIntegrationName}} से <1>{{transferPreviewAmount}}</1> के स्थानांतरण का अनुरोध।",
      "requestToTransferPaymentToClient": "{{selectedIntegrationName}} से {{clientName}} को <1>{{transferPreviewAmount}}</1> के स्थानांतरण का अनुरोध।",
      "requestToTransferSmartToAddress": "{{selectedIntegrationName}} से {{shortToAddress}} को रिले अनुबंध {{shortSmartContractsAddress}} के माध्यम से <1>{{transferPreviewAmount}}</1> के स्थानांतरण का अनुरोध।",
      "requestToTransferSmartToClient": "{{selectedIntegrationName}} से {{clientName}} {{shortToAddress}} को रिले अनुबंध {{shortSmartContractsAddress}} के माध्यम से <1>{{transferPreviewAmount}}</1> के स्थानांतरण का अनुरोध।",
      "requestToTransferToAddress": "{{selectedIntegrationName}} से {{shortToAddress}} को <1>{{transferPreviewAmount}}</1> के स्थानांतरण का अनुरोध।",
      "requestToTransferToClient": "{{selectedIntegrationName}} से {{clientName}} {{shortToAddress}} को <1>{{transferPreviewAmount}}</1> के स्थानांतरण का अनुरोध।",
      "transferPaymentSmartToAddress": "{{selectedIntegrationName}} से रिले अनुबंध {{shortSmartContractsAddress}} के माध्यम से <1>{{transferPreviewAmount}}</1> का स्थानांतरण।",
      "transferPaymentSmartToClient": "{{selectedIntegrationName}} से {{clientName}} को रिले अनुबंध {{shortSmartContractsAddress}} के माध्यम से <1>{{transferPreviewAmount}}</1> का स्थानांतरण।",
      "transferPaymentToAddress": "{{selectedIntegrationName}} से <1>{{transferPreviewAmount}}</1> का स्थानांतरण।",
      "transferPaymentToClient": "{{selectedIntegrationName}} से {{clientName}} को <1>{{transferPreviewAmount}}</1> का स्थानांतरण।",
      "transferSmartToAddress": "{{selectedIntegrationName}} से {{shortToAddress}} को रिले अनुबंध {{shortSmartContractsAddress}} के माध्यम से <1>{{transferPreviewAmount}}</1> का स्थानांतरण।",
      "transferSmartToClient": "{{selectedIntegrationName}} से {{clientName}} {{shortToAddress}} को रिले अनुबंध {{shortSmartContractsAddress}} के माध्यम से <1>{{transferPreviewAmount}}</1> का स्थानांतरण।",
      "transferToAddress": "{{selectedIntegrationName}} से {{shortToAddress}} को <1>{{transferPreviewAmount}}</1> का स्थानांतरण।",
      "transferToClient": "{{selectedIntegrationName}} से {{clientName}} {{shortToAddress}} को <1>{{transferPreviewAmount}}</1> का स्थानांतरण।"
    }
  },
  "doneTransferPage": {
    "awaitingApproval": "यह स्थानांतरण तब तक शुरू नहीं किया जाएगा जब तक इसे {{selectedIntegrationName}} में स्वीकृत नहीं किया जाता।",
    "checkDetails": "देखें क्या हुआ",
    "checkDetails40": "लेनदेन विवरण देखें",
    "depositAddress": "<0>{{amountCrypto}} ~ {{amountFiat}}</0><1></1> {{shortAddress}} में प्राप्त होगा",
    "depositClient": "आप प्राप्त करेंगे <2>{{amountCrypto}} ~ {{amountFiat}}</2> {{clientName}} ({{shortAddress}}) में",
    "directMobileBody": "अपना भुगतान पूरा करने के लिए अपने TAO चेकआउट पेज पर वापस लौटें।",
    "directMobileTitle": "भुगतान प्रारंभ हो गया है",
    "goBackToShift4": "← Shift4 पर वापस जाएँ",
    "goToIntegrationToApprove": "कृपया इस स्थानांतरण को स्वीकृत करने के लिए <1>{{selectedIntegrationName}}</1> पर जाएं।",
    "paymentInitiated": "आपने {{clientName}} को<1></1><2>{{amountCrypto}}</2> <4></4> का भुगतान आरंभ किया है",
    "waiting": "स्थानांतरण तब तक पूर्ण नहीं होते जब तक उन्हें पर्याप्त नेटवर्क पुष्टि नहीं मिलती।"
  },
  "doneVerifyPage": {
    "alreadyVerifiedBody": "पता {{address}} का स्वामित्व पहले ही <4>{{clientName}}</4> के लिए सत्यापित किया जा चुका है।",
    "continueToTransfer": "स्थानांतरण जारी रखें",
    "returnToClient": "{{clientName}} पर लौटें",
    "titleAllSet": "सब सेट!",
    "verifiedBody": "आपने सफलतापूर्वक पता {{address}} का स्वामित्व <4>{{clientName}}</4> के लिए सत्यापित किया है।"
  },
  "drawer": {
    "close": "कनेक्शन मोडल बंद करें"
  },
  "emailVerificationPage": {
    "emailRecievedLoading": "ईमेल प्राप्त हुआ। प्रोसेसिंग...",
    "expiredError": "अनुमोदन ईमेल की अवधि समाप्त हो गई है। कृपया वापस जाएं और पुनः प्रयास करें।",
    "forwardingEmail": "ईमेल अग्रेषित कर रहे हैं",
    "sendEmailButton": "मैंने ईमेल भेज दिया है",
    "steps": {
      "checkInbox": "अपने इनबॉक्स की जाँच करें कि आपने एक नए उपकरण से साइन इन करने की पुष्टि के लिए एक ईमेल प्राप्त किया है।",
      "doNotClick": "ईमेल में दिए गए पुष्टि बटन पर <0>क्लिक न करें</0>।",
      "forwardEmail": "ईमेल को इस सुरक्षित इनबॉक्स में भेजें, जो लॉगिन अनुरोध से मेल खाने के लिए स्वचालित रूप से पुष्टि करेगा।"
    },
    "stillWaitingLoading": "अब भी ईमेल की प्रतीक्षा की जा रही है...",
    "title": "अपनी पहचान की पुष्टि करें",
    "warningTitle": "आगे बढ़ने से पहले इस पूरे संदेश को पढ़ें।"
  },
  "errorHeadlines": {
    "accountTypeNotSupported": "खाता प्रकार समर्थित नहीं है",
    "amountBelowMinimum": "राशि बहुत कम है",
    "amountExceedsMaximum": "राशि बहुत अधिक है",
    "badRequest": "अवैध अनुरोध",
    "balanceNotEnough": "अपर्याप्त धनराशि",
    "binanceTravelRuleRestriction": "यात्रा नियम प्रतिबंध",
    "coinbaseUnavailable": "Coinbase उपलब्ध नहीं है",
    "configurationMismatch": "कॉन्फ़िगरेशन त्रुटि",
    "emptyWalletBalance": "खाली वॉलेट",
    "expiredSmartDeposit": "स्मार्ट जमा की अवधि समाप्त हो गई",
    "failedToGetFundingOptions": "फंडिंग विकल्प त्रुटि",
    "failedToSaveFundingOptions": "सेव असफल हुआ",
    "feeAssetBalanceNotEnough": "अपर्याप्त शुल्क शेष",
    "forbiddenByIntegration": "पहुंच निषिद्ध",
    "fromAccountNotSupported": "निकासी समर्थित नहीं है",
    "integrationError": "एकीकरण त्रुटि",
    "integrationNotAvailable": "एकीकरण उपलब्ध नहीं है",
    "invalidField": "अमान्य जानकारी",
    "invalidFromIntegrationToken": "अमान्य स्रोत टोकन",
    "invalidIntegrationToken": "अमान्य टोकन",
    "invalidToIntegrationToken": "अमान्य गंतव्य टोकन",
    "kycRequired": "के वाई सी आवश्यक",
    "locked": "खाता लॉक किया गया है",
    "missingField": "जानकारी अनुपलब्ध",
    "networkDisabled": "नेटवर्क अक्षम",
    "networkUnsupported": "नेटवर्क समर्थित नहीं है",
    "noAvailableSmartContract": "स्मार्ट अनुबंध उपलब्ध नहीं है",
    "notAuthorizedFromIntegrationToken": "स्रोत अधिकृत नहीं है",
    "notAuthorizedToIntegrationToken": "गंतव्य अधिकृत नहीं है",
    "notFound": "नहीं मिला",
    "notSupported": "समर्थित नहीं है",
    "orderTypeNotSupported": "ऑर्डर प्रकार समर्थित नहीं है",
    "passKeyNotSupported": "पासकी समर्थित नहीं",
    "paymentMethodNotAvailable": "भुगतान विधि उपलब्ध नहीं है",
    "permissionDenied": "प्रवेश अस्वीकृत",
    "previewExpired": "पूर्वावलोकन समाप्त हुआ",
    "refusedByIntegration": "हस्तांतरण अस्वीकृत",
    "satoshiTestRequired": "राशि सीमा पार की",
    "serverFailure": "सर्वर त्रुटि",
    "symbolNotSupported": "प्रतीक समर्थित नहीं है",
    "symbolNotSupportedBySource": "स्रोत समर्थित नहीं है",
    "symbolNotSupportedByTarget": "गंतव्य समर्थित नहीं है",
    "symbolNotSupportedForTrading": "ट्रेडिंग समर्थित नहीं है",
    "timeInForceNotSupported": "टाइम इन फोर्स समर्थित नहीं है",
    "toAccountNotSupported": "जमा समर्थित नहीं है",
    "tooManyRequests": "बहुत अधिक अनुरोध",
    "transferAlreadyRequested": "स्थानांतरण पहले ही अनुरोध किया जा चुका है",
    "twoFaFailed": "अमान्य 2FA कोड",
    "unauthorizedToken": "अनधिकृत टोकन",
    "coinbaseTravelRuleRestriction": "यात्रा नियम प्रतिबंध",
    "withdrawalLocked": "निकासी लॉक की गई है",
    "selfTransferNotAllowed": "स्वयं हस्तांतरण की अनुमति नहीं है",
    "sendAccessDisabled": "पहुंच भेजना अक्षम",
    "tryAgainAfterLogin": "लॉगिन आवश्यक",
    "unableToSend": "हस्तांतरण असफल",
    "userInfoUnavailable": "उपयोगकर्ता जानकारी अनुपलब्ध",
    "webWithdrawalLimitExceeded": "निकासी सीमा पार हो गई है",
    "whitelistAddressRequired": "पता श्वेतसूची आवश्यक है",
    "withdrawalDisabledDueToC2CDepositFreeze": "निकासी अस्थायी रूप से अक्षम",
    "withdrawalDisabledDueToScamRisk": "निकासी अस्थायी रूप से अक्षम",
    "withdrawalDisabledDueToSecurityReset": "निकासी अस्थायी रूप से अक्षम",
    "withdrawalDisabledDueToSuspiciousActivity": "निकासी अस्थायी रूप से अक्षम",
    "withdrawalPendingDepositConfirmation": "निकासी की पुष्टि लंबित",
    "accountNotFound": "खाता नहीं मिला",
    "addressNotAllowlisted": "पता अनुमत सूची में नहीं है",
    "addressAllowlistPending": "पते की स्वीकृति सूची लंबित है",
    "authenticationFailed": "प्रमाणीकरण असफल",
    "belowMinimumFiatDeposit": "न्यूनतम फिएट डिपॉजिट से कम",
    "exceedsApplicationLimit": "आवेदन सीमा से अधिक",
    "invalidCredentials": "अमान्य क्रेडेंशियल्स",
    "mfaNotSupported": "MFA समर्थित नहीं है",
    "withdrawalLockedP2P": "निकासी बंद कर दी गई है",
    "unableToSendContactSupport": "निकासी बंद कर दी गई है",
    "reLogInFaceRecognitionDueToScamRisk": "फिर से प्रयास करें"
  },
  "errorMessages": {
    "amountBelowMinimum": "अनुरोधित राशि इस नेटवर्क पर न्यूनतम अनुमत हस्तांतरण राशि से कम है।",
    "amountExceedsMaximum": "अनुरोधित राशि इस नेटवर्क पर अधिकतम अनुमत हस्तांतरण राशि से अधिक है।",
    "balanceNotEnough": "पर्याप्त शेष राशि नहीं है।",
    "binanceTravelRuleRestriction": "यात्रा नियम प्रतिबंधों के कारण Binance गंतव्य पते पर स्थानांतरण का समर्थन नहीं करता।",
    "coinbaseUnavailable": "Coinbase में एक त्रुटि हुई है। कृपया अपने CB खाते में जाकर जांचें कि स्थानांतरण पूरा हुआ है या नहीं।",
    "default": "एक त्रुटि उत्पन्न हुई है।",
    "emptyWalletBalance": "स्रोत वॉलेट की शेष राशि खाली है।",
    "failedToGetFundingOptions": "वित्तीय विकल्प प्राप्त करने में विफल",
    "failedToSaveFundingOptions": "वित्तीय विकल्प सहेजने में विफल",
    "feeAssetBalanceNotEnough": "हस्तांतरण शुल्क के लिए अपर्याप्त धनराशि।",
    "fromAccountNotSupported": "खाता वर्तमान में क्रिप्टो निकासी का समर्थन नहीं करता है।",
    "integrationNotAvailable": "एकीकरण वर्तमान में उपलब्ध नहीं है।",
    "kycRequired": "स्थानांतरण आरंभ करने में असमर्थ। क्रिप्टो ट्स्थानांतरण सक्षम करने से पहले एकीकरण को खातों से केवाईसी सत्यापन पूरा करना आवश्यक है।",
    "locked": "आपका खाता लॉक है",
    "networkDisabled": "नेटवर्क वर्तमान में अक्षम है और इसका उपयोग नहीं किया जा सकता है।",
    "passKeyNotSupported": "पासकी वर्तमान में समर्थित नहीं है, कृपया जारी रखने के लिए इसे अक्षम करें।",
    "previewExpired": "पूर्वावलोकन की समय सीमा समाप्त हो गई है।",
    "satoshiTestRequired": "यात्रा नियम प्रतिबंधों के कारण, Coinbase API 1000 यूरो से अधिक के स्थानांतरण का समर्थन नहीं करता। कृपया कम राशि के साथ पुनः प्रयास करें।",
    "symbolNotSupported": "चिह्न को एकीकरण द्वारा समर्थित नहीं है।",
    "symbolNotSupportedBySource": "सूत्र वॉलेट द्वारा अनुरोधित नेटवर्क पर स्थानांतरण के लिए चिह्न समर्थित नहीं है।",
    "symbolNotSupportedByTarget": "अनुरोधित सिक्के के लिए जमा पता नहीं मिल सका।",
    "toAccountNotSupported": "गंतव्य खाता वर्तमान में क्रिप्टो जमा नहीं करता है।",
    "tooManyRequests": "कृपया बाद में पुनः प्रयास करें।",
    "transferAlreadyRequested": "स्थानांतरण पहले से अनुरोधित है।",
    "twoFaFailed": "द्वि-कारक सत्यापन विफल। कृपया पुनः प्रयास करें।",
    "coinbaseTravelRuleRestriction": "ग्लोबल ट्रैवल नियम प्रतिबंधों के कारण, आपके देश से वर्तमान में Coinbase API स्थानांतरण का समर्थन नहीं करता है।",
    "withdrawalLocked": "आपकी सुरक्षा के लिए, खाता सेटिंग्स में परिवर्तन के बाद 24 घंटे के लिए निकासी अक्षम कर दी गई है। कृपया बाद में पुनः प्रयास करें।",
    "accountNotFound": "आपका खाता (खाते) प्राप्त करने में असमर्थ।",
    "addressNotAllowlisted": "Coinbase से निकासी शुरू करने में असमर्थ। आपको इस प्राप्तकर्ता पते को अपनी अनुमति सूची में जोड़ना होगा: https://www.coinbase.com/settings/allowlist",
    "addressAllowlistPending": "यह प्राप्तकर्ता पता आपकी अनुमति सूची में जोड़ा गया है और एक होल्ड के लिए लंबित है।",
    "authenticationFailed": "चयनित एकीकरण के साथ प्रमाणीकरण में असमर्थ।",
    "belowMinimumFiatDeposit": "राशि न्यूनतम फिएट जमा सीमा से कम है।",
    "exceedsApplicationLimit": "स्थानांतरण राशि अनुप्रयोग सीमा से अधिक है।",
    "invalidCredentials": "अमान्य क्रेडेंशियल्स। कृपया पुनः प्रयास करें।",
    "mfaNotSupported": "इस ऑपरेशन के लिए बहु-कारक प्रमाणीकरण समर्थित नहीं है।",
    "selfTransferNotAllowed": "आप एक खाते से उसी खाते में स्थानांतरण नहीं कर सकते।",
    "sendAccessDisabled": "इस खाते के लिए भेजने की अनुमति निष्क्रिय कर दी गई है, जिसके कारण निकासी शुरू नहीं की जा सकती।",
    "tryAgainAfterLogin": "कृपया लॉग इन करने के बाद पुनः प्रयास करें।",
    "unableToSend": "स्थानांतरण भेजने में असमर्थ। कृपया फिर से प्रयास करें।",
    "userInfoUnavailable": "उपयोगकर्ता जानकारी प्राप्त करने में असमर्थ। कृपया पुनः प्रयास करें।",
    "webWithdrawalLimitExceeded": "आपने Binance वेब संस्करण के लिए दैनिक अधिकतम निकासी सीमा पार कर ली है।",
    "whitelistAddressRequired": "गंतव्य पते को श्वेतसूची में होना चाहिए।",
    "withdrawalDisabledDueToC2CDepositFreeze": "आपकी संपत्तियों की सुरक्षा के लिए, आपके कुछ C2C जमा की गई संपत्तियों को 24 घंटे के लिए फ्रीज करना आवश्यक है। 24 घंटे के बाद, फ्रीज की गई स्थिति स्वतः हटा दी जाएगी और आप क्रिप्टो निकाल सकेंगे। फ्रीजिंग अवधि के दौरान, आपकी साइट पर लेनदेन प्रभावित नहीं होंगे, कृपया Binance की लेनदेन सेवाओं का सामान्य रूप से उपयोग करें।",
    "withdrawalDisabledDueToScamRisk": "आपकी निकासी को उच्च जोखिम के रूप में पहचाना गया है। आपके धन की सुरक्षा के लिए, आपके खाते से निकासी 1 घंटे के लिए अस्थायी रूप से अक्षम कर दी गई है।",
    "withdrawalDisabledDueToSecurityReset": "आपके खाते की निकासी कार्यक्षमता हालिया सुरक्षा सत्यापन रिसेट के कारण अस्थायी रूप से अक्षम कर दी गई है।",
    "withdrawalDisabledDueToSuspiciousActivity": "संदिग्ध गतिविधि के कारण आपकी निकासी कार्यक्षमता अक्षम कर दी गई है। कृपया Binance पर सत्यापन प्रक्रिया पूरी करें। यदि आप सत्यापित करने में असमर्थ हैं, तो ग्राहक सहायता से संपर्क करें। यदि आपने हाल ही में सत्यापन पूरा कर लिया है, तो कृपया एक क्षण प्रतीक्षा करें और पुनः प्रयास करें।",
    "withdrawalPendingDepositConfirmation": "आपकी जमा राशि निकासी के लिए आवश्यक अनलॉक पुष्टि से मेल नहीं खाती है। अधिक जानकारी के लिए कृपया लेन-देन इतिहास देखें।",
    "invalidFromIntegrationToken": "हस्तांतरण शुरू करने में असमर्थ। इस खाते में प्रमाणीकृत करने के लिए उपयोग किया गया टोकन इस क्रिया को करने के लिए अधिकृत नहीं है।",
    "invalidToIntegrationToken": "गंतव्य की पहचान करने में असमर्थ।",
    "notAuthorizedFromIntegrationToken": "हस्तांतरण शुरू करने में असमर्थ। इस खाते में प्रमाणीकृत करने के लिए उपयोग किया गया टोकन इस क्रिया को करने के लिए अधिकृत नहीं है।",
    "notAuthorizedToIntegrationToken": "हस्तांतरण शुरू करने में असमर्थ। इस खाते में प्रमाणीकृत करने के लिए उपयोग किया गया टोकन इस क्रिया को करने के लिए अधिकृत नहीं है।",
    "configurationMismatch": "हस्तांतरण शुरू करने में असमर्थ। खाते का विन्यास अनुरोधित स्थानांतरण से मेल नहीं खाता।",
    "refusedByIntegration": "हस्तांतरण शुरू करने में असमर्थ। एकीकरण ने अनुरोध को अस्वीकार कर दिया है।",
    "noAvailableSmartContract": "कोई स्मार्ट अनुबंध उपलब्ध नहीं है",
    "expiredSmartDeposit": "स्मार्ट जमा की समय सीमा समाप्त हो चुकी है। स्मार्ट अनुबंध को हटा दिया गया है।",
    "withdrawalLockedP2P": "आपकी सुरक्षा के लिए, P2P खरीद के बाद 24 घंटे के लिए निकासी अक्षम कर दी गई है। कृपया बाद में पुनः प्रयास करें।",
    "unableToSendContactSupport": "आप फिलहाल क्रिप्टो नहीं भेज सकते। कृपया कॉइनबेस सहायता से संपर्क करें।",
    "reLogInFaceRecognitionDueToScamRisk": "आपकी सुरक्षा के लिए, कृपया दोबारा लॉगिन करें और फेस पहचान प्रक्रिया पूरी करें।"
  },
  "errorPage": {
    "title": "एक त्रुटि हुई है।"
  },
  "exitPage": {
    "body": "आपकी प्रगति खो जाएगी।",
    "continue": "नहीं, जारी रखें",
    "exit": "हाँ, बाहर जाएँ",
    "title": "क्या आप सुनिश्चित हैं कि आप बाहर जाना चाहते हैं?"
  },
  "externalDirectMobileWallet": {
    "actionRefusedError": "कार्य अस्वीकृत",
    "actionRefusedRetryText": "कृपया अपने {{clientName}} ऐप पर वापस जाएं",
    "actionRefusedText": "आपने कार्रवाई को अस्वीकार कर दिया है।",
    "connectionWalletAction": "आपने सफलतापूर्वक अपने {{integrationName}} को जोड़ लिया है।",
    "continueInApp": "कृपया अपनी {{clientName}} ऐप में जारी रखें।",
    "continuePaymentInApp": "अपना {{clientName}} खरीदारी जारी रखने के लिए अपनी चेकआउट प्रक्रिया पर लौटें।",
    "defaultAction": "आपने सफलतापूर्वक कार्य पूरा कर लिया है।",
    "processingError": "प्रोसेसिंग त्रुटि",
    "processingText": "कुछ गलत हो गया।",
    "sessionNotFoundError": "सत्र नहीं मिला",
    "signedMessageAction": "आपने अपने {{integrationName}} का स्वामित्व सफलतापूर्वक सत्यापित कर लिया है।",
    "transactionAction": "आपने लेन-देन को सफलतापूर्वक प्रारंभ कर लिया है।",
    "tryAgainText": "कृपया बाद में पुनः प्रयास करें।"
  },
  "externalHardwareWalletInitial": {
    "invalidCode": "अमान्य कोड। कृपया पुनः प्रयास करें"
  },
  "externalHardwareWalletMainPage": {
    "mobileBody": "इस अनुभव को पूरा करने के लिए आपके हार्डवेयर वॉलेट को <1>डेस्कटॉप</1> डिवाइस से कनेक्ट किया जाना चाहिए।",
    "mobileTitle": "इस लिंक को डेस्कटॉप डिवाइस पर खोलें"
  },
  "externalInitialScreen": {
    "title": "अपने मोबाइल डिवाइस पर <1></1> प्रदर्शित एक बार के कोड को दर्ज करें"
  },
  "externalTransferCallbackPage": {
    "continue": "{{clientName}} पर जारी रखें",
    "transferRequested": "स्थानांतरण का अनुरोध किया गया है, कृपया वापस {{clientName}} पर जाएँ",
    "updatingTransfer": "स्थानांतरण स्थिति अपडेट हो रही है..."
  },
  "facePage": {
    "completedButton": "मैंने सत्यापन पूरा कर लिया है",
    "desktopStep1": "वास्तव में आप ही लॉग इन कर रहे हैं, यह सुनिश्चित करने के लिए फेस सत्यापन पूरा करने हेतु क्यूआर कोड स्कैन करें।",
    "desktopStep2": "फिर अपने खाते से लिंकिंग समाप्त करने के लिए यहाँ लौटें।",
    "mobileStep1": "यह सुनिश्चित करने के लिए फेस वेरिफिकेशन पूरा करें कि वास्तव में आप लॉग इन करने की कोशिश कर रहे हैं।",
    "mobileStep2": "अपने ऐप को खोलने और फेस वेरिफिकेशन पूरा करने के लिए <1>ओपन {{integrationName}} ऐप</1> पर क्लिक करें।",
    "mobileStep3": "अपने खाते को लिंक करना जारी रखने के लिए यहाँ वापस लौटें।",
    "openApp": "{{integrationName}} ऐप खोलें",
    "reopenApp": "{{integrationName}} ऐप पुनः खोलें",
    "title": "सत्यापन"
  },
  "fields": {
    "apiKey": "एपीआई कुंजी",
    "apiSecret": "एपीआई गुप्त",
    "authToken": "प्राधिकरण टोकन",
    "challengeCode": "चुनौती कोड",
    "clientId": "क्लाइंट आईडी",
    "clientSecret": "क्लाइंट सीक्रेट",
    "email": "ईमेल",
    "emailOrUsername": "ईमेल या उपयोगकर्ता नाम",
    "mfaCode": "एमएफए कोड",
    "passphrase": "पासफ़्रेज़",
    "password": "पासवर्ड",
    "phone": "फोन नंबर",
    "privateKey": "निजी कुंजी",
    "secretKey": "गुप्त कुंजी",
    "tradePin": "व्यापार पिन",
    "userId": "उपयोगकर्ता आईडी",
    "username": "उपयोगकर्ता नाम"
  },
  "fullScreenSpinner": {
    "linking": "आपका खाता लिंक किया जा रहा है...",
    "loading": "अभी भी काम कर रहा है..."
  },
  "fundingLoadingOverlay": {
    "loading": "लोड हो रहा है..."
  },
  "fundingMethodFees": {
    "fee": {
      "conversion": "{{integrationName}} {{conversionFromCurrency}} से {{conversionToCurrency}} में रूपांतरण शुल्क",
      "deposit": "{{integrationName}} जमा शुल्क",
      "purchase": "{{integrationName}} {{fiatSymbol}} से {{cryptocurrencySymbol}} खरीदारी शुल्क",
      "withdrawal": "{{integrationName}} निकासी शुल्क"
    },
    "info": {
      "conversion": "आपके {{conversionFromSymbol}} को {{conversionToSymbol}} में बदलने की प्रक्रिया में {{integrationName}} द्वारा लिया जाने वाला शुल्क।",
      "purchase": "शुल्क जो {{integrationName}} आपके {{symbol}} की खरीद को सुगम बनाने के लिए वसूल करेगा।",
      "withdrawal": "आपके {{symbol}} निकासी को सुगम बनाने के लिए {{integrationName}} जो शुल्क लेंगे।"
    }
  },
  "fundingMethodsList": {
    "buyingPower": "खरीदने की क्षमता",
    "cryptocurrencyBalance": "{{symbol}} शेष राशि",
    "noneSelected": "कोई चयन नहीं किया गया",
    "paymentMethodDepositUsage": "लिंक किया हुआ भुगतान तरीका",
    "stablecoinConversion": "स्टेबलकॉइन रूपांतरण",
    "withAdditional_one": "{{mainOption}} + {{count}} अन्य",
    "withAdditional_other": "{{mainOption}} + {{count}} अन्य"
  },
  "fundingOptionUnavailabilityReason": {
    "buyingPowerUsageNotSupported": "{{integrationName}} {{assetName}} खरीदने के लिए इस फंडिंग विधि का उपयोग करने का समर्थन नहीं करता है।",
    "coveredByExistingCryptocurrencyBalance": "इस खरीदारी के लिए आपके पास पहले से ही पर्याप्त {{assetName}} शेष है, जिसमें अतिरिक्त फंडिंग विधियों की आवश्यकता नहीं है।",
    "coveredByOtherFundingOptions": "इस लेन-देन के लिए इस फंडिंग विधि का समर्थन नहीं किया गया है।",
    "currencyNotSupported": "क्रिप्टो को गैर-USD फंडिंग विधि के साथ खरीदना अभी तक समर्थित नहीं है।",
    "depositAmountLimitExceeded": "यह खरीदारी इस फंडिंग विधि के लिए 1 दिन में {{integrationName}} की अधिकतम जमा सीमा को पार कर देगी।",
    "depositCountLimitReached": "यह फंडिंग विधि पहले ही {{integrationName}} की एक दिन में अनुमत अधिकतम जमा संख्या तक पहुँच चुकी है।",
    "depositsNotSupported": "इस लेन-देन के लिए इस फंडिंग विधि का समर्थन नहीं किया गया है।",
    "instantDepositLimitExceeded": "इस खरीदारी के लिए इस फंडिंग विधि की त्वरित जमा सीमा अपर्याप्त है।",
    "instantDepositsNotSupported": "यह फंडिंग विधि त्वरित जमाओं का समर्थन नहीं करती है, इसलिए इसे इस खरीदारी के लिए उपयोग नहीं किया जा सकता है।",
    "insufficientBalance": "इस खरीदारी के लिए शेष राशि अपर्याप्त है।",
    "maximumDepositLimitViolated": "राशि इस फंडिंग विधि की अधिकतम जमा सीमा से ऊपर है।",
    "minimumDepositLimitViolated": "राशि इस फंडिंग विधि की न्यूनतम जमा सीमा से नीचे है।",
    "paymentMethodTypeNotSupported": "इस फंडिंग विधि का अभी तक समर्थन नहीं किया गया है।",
    "unknown": "यह फंडिंग विकल्प अनुपलब्ध है।"
  },
  "fundingPage": {
    "activatePaymentMethod": "{{selectedIntegrationName}} पर भुगतान विधि सक्रिय करें",
    "aproximateFiat": "~{{amountInFiat}}",
    "balanceAmount": "शेष राशि: {{amount}}",
    "balanceAmountWithConversion": "शेष राशि: ~{{amount}} ({{conversionSymbols}})",
    "balances": "शेष राशि",
    "balanceWithAproximateFiat": "शेष राशि: {{amount}} ~ {{amountInFiat}}",
    "buyingPower": "खरीदने की क्षमता",
    "changeAmount": "या स्थानांतरण की राशि को {{availableAmount}} में बदलें।",
    "changePreferredPaymentMethod": "पसंदीदा भुगतान विधि बदलें",
    "changePreferredToken": "पसंदीदा टोकन बदलें",
    "cryptoConversion": "क्रिप्टो मुद्रा रूपांतरण",
    "description": "कुल: {{amount}} ~ {{amountInFiat}}",
    "instantCashAvailable": "(तत्काल नकद उपलब्ध: {{amountInFiat}})",
    "insufficientFunds": "अपर्याप्त धनराशि",
    "linkedPaymentMethods": "लिंक की गई भुगतान विधि(एं)",
    "noPaymentMethods": "कोई लिंक की गई भुगतान विधियाँ नहीं है।",
    "noTokensAvailableForConversion": "रूपांतरण के लिए कोई टोकन उपलब्ध नहीं है",
    "save": "सहेजें",
    "selectFundingMethodAvailablity": "आपके द्वारा चुनी गई फंडिंग विधियों में {{selectedAvailableAmount}} है। कृपया {{neededAmount}} को स्थानांतरित करने के लिए अतिरिक्त फंडिंग विधियाँ चुनें।",
    "selectFundingMethods": "कृपया <2>{{amount}} ~ {{amountInFiat}}</2> स्थानांतरित करने के लिए वित्त पोषण पद्धति(यां) चुनें।",
    "selectFundingMethodsTitle": "कोई फंडिंग विधि चयनित नहीं है",
    "selectOtherHoldings": "अन्य होल्डिंग्स से चुनें",
    "symbolBalance": "{{symbol}} शेष",
    "title": "फंडिंग विधियाँ"
  },
  "gasFeeUpdateDrawerContent": {
    "approvePayment": "भुगतान स्वीकृत करें",
    "cancel": "रद्द करें",
    "description": "गैस शुल्क मूल अनुमान से अधिक है।",
    "ifDontComplete": "यदि आप भुगतान नहीं करते हैं, तो आपका {{token}} शेष आपके {{selectedIntegrationName}} खाते में रहेगा।",
    "newEstimate": "नया अनुमान",
    "originalEstimate": "मूल अनुमान",
    "title": "गैस शुल्क अपडेट"
  },
  "generateKeyPage": {
    "establishedInClient": "आपने<1></1><2>{{clientName}}</2> में सफलतापूर्वक निर्बाध अपडेट स्थापित कर दिए हैं।",
    "establishedInThisApp": "आपने <1></1><2>इस ऐप</2> में निर्बाध अपडेट सफलतापूर्वक स्थापित कर दिए हैं।",
    "linkedToInClient": "आपने<1></1><2>{{selectedIntegrationName}}</2> को सफलतापूर्वक <5>{{clientName}}</5> से जोड़ दिया है।",
    "linkedToThisApp": "आपने सफलतापूर्वक <1></1><2>{{selectedIntegrationName}}</2> को <5>इस एप्लिकेशन</5> से जोड़ दिया है।",
    "nextStep": "अब हम <2>निर्बाध अपडेट</2> के लिए एक कुंजी बनाएंगे ताकि आपको फिर से लॉग इन न करना पड़े",
    "tempAccess": "मैं केवल अस्थायी एक्सेस चाहता हूँ"
  },
  "getBrokerAccessTokenErrors": {
    "add2FA": "कृपया 2FA एप्लिकेशन को कनेक्ट करें। और पुनः प्रयास करें।",
    "identityVerificationRequired": "API कुंजी सुविधा का उपयोग करने के लिए आपको पहचान सत्यापन पूरा करना आवश्यक है। जारी रखने के लिए कृपया पहचान सत्यापन पूरा करें।",
    "invalidCredentials": "अवैध लॉगिन प्रमाण-पत्र। कृपया पुनः प्रयास करें।",
    "maximumApiKeyLimitExceeded": "अधिकतम अनुमत API कुंजी सीमा तक पहुँच गया है। कृपया जारी रखने के लिए एक अप्रयुक्त कुंजी को हटा दें।",
    "unsupportedCountryErrorMessage": "हम वर्तमान में आपके खाते का समर्थन नहीं करते हैं",
    "wrongEmailCode": "गलत ईमेल कोड, कृपया पुनः प्रयास करें",
    "wrongTotpCode": "गलत प्रामाणिकता कोड, कृपया पुनः प्रयास करें"
  },
  "handleExternalTransferPage": {
    "detailButton": "देखिए क्या हुआ",
    "error": "स्थानांतरण निष्पादित करने में विफल",
    "loadingLabel": "आपके स्थानांतरण की पुष्टि हो रही है...",
    "networkConfirmations": "स्थानांतरण तब तक पूर्ण नहीं होते जब तक उन्हें पर्याप्त नेटवर्क पुष्टि नहीं मिलती।",
    "notInitiatedUntilApproved": "यह स्थानांतरण तब तक शुरू नहीं किया जाएगा जब तक इसे {{selectedIntegrationName}} में स्वीकृत नहीं किया जाता।",
    "recievedDetails": "आपको {{clientName}} ({{shortAddress}}) में <1>{{amountStr}}</1> प्राप्त होंगे",
    "requestRecieved": "आपका {{destination}} के लिए स्थानांतरण अनुरोध {{selectedIntegrationName}} द्वारा प्राप्त किया गया था",
    "revolutApproveInfo": "यह स्थानांतरण तब तक शुरू नहीं होगा जब तक कि इसे Revolut ऐप में स्वीकृत नहीं किया जाता",
    "transactionComplete": "लेन-देन पूर्ण"
  },
  "handleOauthPage": {
    "error": "आपका खाता लिंक करने में विफल। {{error}}"
  },
  "hardwareWalletDrawerContent": {
    "body": "{{clientName}} सुरक्षित कनेक्शन सुविधा के लिए {{selectedIntegrationName}} के साथ Mesh का उपयोग करता है।",
    "connectAction": "{{selectedIntegrationName}} के साथ जुड़े"
  },
  "ineligibleReason": {
    "amountBelowMinimumDescription": "{{requestedAmount}} की अनुरोधित स्थानांतरण राशि {{integrationName}} द्वारा {{minimumAmount}} के न्यूनतम से कम है {{network}} नेटवर्क पर स्थानांतरण के लिए।",
    "balanceBelowMinimumDescription": "आपकी {{currentBalance}} शेष राशि {{network}} नेटवर्क पर स्थानांतरित करने के लिए {{integrationName}} की {{minimumAmount}} न्यूनतम राशि से कम है।",
    "belowMinimum": "{{integrationName}} के न्यूनतम से कम",
    "belowRequestedAmountDescription": "आपका {{balance}} शेष राशि अनुरोधित स्थानांतरण राशि + शुल्क को कवर करने के लिए {{amount}} से कम है।",
    "gasFeeAssetBalanceNotEnoughDescription": "आपका {{balance}} शेष राशि {{network}} नेटवर्क पर अनुमानित {{gasFee}} गैस फ़ीस को कवर करने के लिए अपर्याप्त है।",
    "insufficientBalance": "अपर्याप्त शेष राशि",
    "insufficientBalanceDescription": "आपका {{currentBalance}} शेष राशि इस स्थानांतरण के लिए न्यूनतम से कम है।",
    "notEligible": "इस स्थानांतरण के लिए योग्य नहीं",
    "notEligibleDescription": "इस स्थानांतरण के लिए {{symbol}} स्वीकर नहीं किया गया है।",
    "notSupportedByInstitution": "वर्तमान में {{integrationName}} द्वारा समर्थित नहीं है",
    "notSupportedForTransferBySource": "{{integrationName}} द्वारा समर्थित नहीं है",
    "nyCoinbaseUserRestrictions": "NY मल्टी-चेन समर्थन प्रतिबंधों के कारण {{network}} पर {{symbol}} इस ट्रांसफ़र के लिए स्वीकार्य नहीं है।",
    "symbolDoesNotMatch": "{{clientName}} द्वारा समर्थित नहीं है",
    "symbolDoesNotMatchDescription": "इस स्थानांतरण के लिए {{symbol}} स्वीकार नहीं किया गया है।"
  },
  "initialLedgerScreen": {
    "title": "अपना डिवाइस चालू करें और अनलॉक करें"
  },
  "initialScreen": {
    "accountTitle": "यह एप्लिकेशन आपके खाते को सुरक्षित रूप से लिंक करेगा",
    "clientNameAccountTitle": "{{clientName}} आपके खाते को सुरक्षित रूप से लिंक करेगा",
    "clientNameWalletTitle": "{{clientName}} आपके वॉलेट को सुरक्षित रूप से जोड़ेगा",
    "walletTitle": "यह एप्लिकेशन आपके वॉलेट को सुरक्षित रूप से जोड़ेगा"
  },
  "initialSteps": {
    "agreement": "\"जारी रखें\" का चयन करके आप <1></1><2>अंतिम उपयोगकर्ता नियम और शर्तें</2> से सहमत हैं",
    "credentials": "आपकी साइन-इन क्रेडेंशियल्स कभी भी संग्रहीत नहीं की जाती हैं",
    "encryption": "आपके डेटा को हर समय एन्क्रिप्ट किया जाता है",
    "explicitApproval": "स्थानांतरण शुरू करने के लिए हमेशा स्पष्ट अनुमति की आवश्यकता होती है",
    "thirdParty": "आपकी संपत्ति कभी भी तीसरे पक्ष के संपर्क में नहीं आती"
  },
  "initialVerifyPage": {
    "content40": "पुष्टि करें कि आप इस वॉलेट के मालिक हैं",
    "drawerTitle": "अपने वॉलेट में हस्ताक्षर अनुरोध<1></1> को स्वीकृति दें",
    "item1Body": "आपसे {{selectedIntegrationName}} में एक संदेश पर हस्ताक्षर करने के लिए कहा जाएगा जो इस वॉलेट के स्वामित्व की पुष्टि करता है।",
    "item1Title": "{{clientName}} को आपका पता सत्यापित करना होगा",
    "item2Body": "हस्ताक्षर करने से किसी भी तरह से {{clientName}} को आपके वॉलेट के साथ लेन-देन करने की अनुमति नहीं मिलती है।",
    "item2Title": "तेज़, सुरक्षित और मुफ्त",
    "monitoringLabel": "हस्ताक्षर की निगरानी हो रही है...",
    "resendAction": "हस्ताक्षर अनुरोध पुनः भेजें",
    "title": "लगभग हो चुका है!",
    "verifyAction": "पता सत्यापित करें",
    "verifyingLabel": "हस्ताक्षर सत्यापित किया जा रहा है..."
  },
  "ipWhiteListPage": {
    "addIp": "नीचे दिए गए IP पते को एक विश्वसनीय IP के रूप में जोड़ें",
    "clickOnEdit": "प्रतिबंध संपादित करें पर क्लिक करें",
    "copyIpTitle": "IP पता",
    "description": "<0>Binance</0> ट्रेड और स्थानांतरण अनुरोधों की वैधता सुनिश्चित करने के लिए एपीआई उपयोगकर्ताओं को IP पतों को श्वेत सूची में जोड़ने की आवश्यकता होती है।",
    "findKey": "इस कनेक्शन के लिए उपयोग की गई कुंजी ढूँढें",
    "openLink": "<2><0>Binance एपीआई प्रबंधन</0></2> खोलें",
    "requirementsTitle": "यदि आप इस कनेक्शन के माध्यम से ट्रेड या स्थानांतरण करने की योजना बना रहे हैं:",
    "title": "इससे पहले कि आप आगे बढ़ें इस IP पते को श्वेत सूची में जोड़ें"
  },
  "kycDonePage": {
    "successMessage": "आपने सफलतापूर्वक अपनी पहचान सत्यापित कर ली है और अपने {{integrationName}} खाते में क्रिप्टो स्थानांतरण सक्षम कर दिया है"
  },
  "kycInitialPage": {
    "description": "आपकी सुरक्षा के लिए, {{integrationName}} यह आवश्यक मानता है कि आपके क्रिप्टो ट्रांसफर करने से पहले आपको अपनी पहचान सत्यापित करनी होगी।",
    "steps": {
      "completeVerification": "अपने पहचान को सत्यापित करने के लिए प्रक्रिया पूरी करें और अपने खाते से स्थानांतरण सक्षम करें",
      "navigateCrypto": "क्रिप्टो टैब पर जाएं, उस संपत्ति को खोलें जिसे आप स्थानांतरित करना चाहते हैं और \"भेजें\" पर क्लिक करें",
      "openAccount": "अपना {{integrationName}} खाता खोलें",
      "returnToScreen": "इस स्क्रीन पर लौटें"
    },
    "title": "अपने {{integrationName}} खाते में स्थानांतरण सक्षम करें",
    "verifiedButton": "मैंने {{integrationName}} के साथ अपनी पहचान सत्यापित की है"
  },
  "kycPendingPage": {
    "connectAnother": "अन्य खाता कनेक्ट करें",
    "description": "पहचान सत्यापन में <1>1 - 3 कार्यदिवस</1> लग सकते हैं। एक बार सत्यापन पूरा हो जाने पर और आपके खाते में स्थानांतरण सक्षम हो जाते हैं, आप यहां लौट सकते हैं इस लेन-देन को पूरा करने के लिए।",
    "title": "स्वीकृति लंबित"
  },
  "kycRobinhoodPage": {
    "clickContinue": "{{selectedIntegrationName}} खोलने के लिए <1>जारी रखें</1> पर क्लिक करें।",
    "clickContinueAfterActivated": "{{selectedIntegrationName}} में क्रिप्टो स्थानांतरण सक्रिय करने के बाद, अपना स्थानांतरण जारी रखने के लिए नीचे <5>जारी रखें</5> पर क्लिक करें।",
    "completeVerification": "पहचान सत्यापन पूरा करें और/या दो-कारक प्रमाणीकरण विधि जोड़ें।",
    "connectAnother": "अन्य खाता कनेक्ट करें",
    "note": "कृपया ध्यान दें: जब आप लौटेंगे तो इस स्थानांतरण को शुरू करने के लिए आपको अपने {{selectedIntegrationName}} खाते में वापस लॉग इन करना पड़ सकता है।",
    "return": "स्थानांतरण पूरा करने के लिए यहां लौटें।",
    "title": "अपने खाते में स्थानांतरण सक्षम करें"
  },
  "ledgerBluetooth": {
    "step1": "<1>ब्लूटूथ</1> विंडो से अपना डिवाइस चुनें",
    "step2": "कनेक्शन पूरा करने के लिए ब्लूटूथ विंडो और अपने लेजर डिवाइस में दिए निर्देशों का पालन करें"
  },
  "ledgerConnection": {
    "bluetoothConnect": "ब्लूटूथ से कनेक्ट करें",
    "connectionQuestion": "आप अपने लेजर को कैसे कनेक्ट करना चाहेंगे?",
    "usbConnect": "यूएसबी के साथ कनेक्ट करें"
  },
  "ledgerDeviceConnected": {
    "clientVerifyLabel": "{{clientName}} को आपका वॉलेट सत्यापित करना होगा",
    "clientVerifyText": "आपके लेज़र डिवाइस में एक संदेश हस्ताक्षर करने के लिए प्रेरित किया जाएगा जो पुष्टि करता है की आप इस वॉलेट के मालिक हैं।",
    "secureLabel": "तेज़, सुरक्षित और मुफ्त",
    "secureText": "हस्ताक्षर करने से किसी भी तरह से {{clientName}} को आपके वॉलेट के साथ लेन-देन करने की अनुमति नहीं मिलती है।",
    "title": "लगभग हो चुका है!"
  },
  "ledgerError": {
    "incorrectAppError": "आपके डिवाइस पर गलत अनुप्रयोग खुला है। कृपया सही ऐप खोलें और पुनः प्रयास करें।",
    "lockedError": "आपका डिवाइस लॉक है। कृपया इसे अनलॉक करें और पुनः प्रयास करें।",
    "noDeviceError": "कोई डिवाइस चयनित नहीं है। कृपया एक डिवाइस का चयन करें और पुनः प्रयास करें।",
    "notSelectedError": "कोई एप्लिकेशन चयनित नहीं है। कृपया एक एप्लिकेशन का चयन करें और पुनः प्रयास करें।",
    "rejectError": "उपयोगकर्ता ने ऑपरेशन को अस्वीकार कर दिया है। कृपया पुनः प्रयास करें।",
    "title": "कनेक्शन असफल रहा",
    "transportError": "आपके डिवाइस के साथ एक ट्रांसपोर्ट त्रुटि हुई है।",
    "transportLockedError": "ट्रांसपोर्ट लॉक है। कृपया अपने डिवाइस को अनलॉक करें और पुनः प्रयास करें।",
    "unexpectedError": "एक अप्रत्याशित त्रुटि हुई।",
    "unknownError": "आपके लेजर डिवाइस में एक अज्ञात गलती हुई।"
  },
  "ledgerOpenApp": {
    "title": "अपने डिवाइस में {{network}} ऐप खोलें"
  },
  "ledgerSignError": {
    "body": "आपने अपने वॉलेट को सत्यापित करने के लिए अनुरोध को अस्वीकार कर दिया है।",
    "title": "सत्यापन विफल"
  },
  "ledgerSignMessage": {
    "rippleBody": "ध्यान दें: XRP के लिए, आपको न्यूनतम मानों के साथ एक डमी लेनदेन दिखाई देगी। यह केवल आपके वॉलेट का सत्यापन करने के लिए है और इससे कोई खर्च नहीं होगा या कोई फंड नहीं भेजा जाएगा।",
    "title": "अपने डिवाइस पर संदेश की समीक्षा करें और हस्ताक्षर करें"
  },
  "ledgerUSB": {
    "step1": "<1>यूएसबी</1> विंडो से अपना डिवाइस चुनें",
    "step2": "कनेक्शन पूरा करने के लिए यूएसबी विंडो और अपने लेजर डिवाइस में दिए निर्देशों का पालन करें"
  },
  "loginDeviceVerifiedPage": {
    "loginButton": "लॉगिन पर जाएं",
    "subtitle": "लॉगिन के लिए आगे बढ़ें।",
    "title": "आपका डिवाइस स्वीकृत है।"
  },
  "mfaError": {
    "default": "गलत कोड, कृपया पुनः प्रयास करें"
  },
  "mfaHint": {
    "email": "अपने ईमेल की जाँच करें",
    "phone": "एसएमएस संदेश के लिए अपने फोन की जाँच करें",
    "sandbox": "संकेत: {{hint}}",
    "totp": "अपने प्रमाणीकरण ऐप की जाँच करें"
  },
  "mfaInstructionsText": {
    "email": "एक-बार उपयोग करने वाला कोड दर्ज करें जो <2>{{selectedIntegrationName}}</2> ने आपके ईमेल पर भेजा है।",
    "paymentFlow": "इस भुगतान की पुष्टि के लिए अपना वन-टाइम कोड दर्ज करें ताकि यह सुनिश्चित किया जा सके कि वास्तव में आप ही इसे प्रारंभ कर रहे हैं।",
    "phone": "अपने फोन पर <2>{{selectedIntegrationName}}</2> से भेजे गए वन-टाइम कोड को दर्ज करें।",
    "totp": "अपने <1>{{selectedIntegrationName}}</1> से लिंक किए गए प्रमाणक ऐप द्वारा प्रदान किए गए वन-टाइम कोड को दर्ज करें।",
    "tradingPin": "कृपया अपने <2>{{selectedIntegrationName}}</2> खाते से जुड़े ट्रेडिंग पिन कोड दर्ज करें।",
    "transferFlow": "इस हस्तांतरण की पुष्टि के लिए अपना वन-टाइम कोड दर्ज करें ताकि यह सुनिश्चित किया जा सके कि वास्तव में आप ही इसे प्रारंभ कर रहे हैं।",
    "twoFactor": "कृपया अपने <1>{{selectedIntegrationName}}</1> खाते में आपके द्वारा कॉन्फ़िगर की गई दो-कारक प्रमाणीकरण विधि द्वारा प्रदान किए गए कोड को दर्ज करें।"
  },
  "mfaPage": {
    "enterCode": "अपने वन-टाइम कोड को दर्ज करें ताकि यह पुष्टि हो सके कि वास्तव में आप ही लॉग इन करने की कोशिश कर रहे हैं।<1></1>।",
    "enterPin": "अपना ट्रेडिंग पिन दर्ज करें",
    "title": "सत्यापन",
    "verify": "सत्यापित करें"
  },
  "mfaSetupPage": {
    "emailButton": "ईमेल सत्यापन सेट करें",
    "emailSubtitle": "अपने <2>{{selectedIntegrationName}}</2> खाते में एक ईमेल जोड़ने के लिए नीचे दिए बटन पर क्लिक करें।",
    "keyGenerationBody": "आपकी सुरक्षा के लिए, <1>{{selectedIntegrationName}}</1> यह आवश्यक है कि उपयोगकर्ताओं को कुंजी उत्पन्न करने के लिए ईमेल और प्रमाणीकरण ऐप MFA विधियाँ सक्षम हों",
    "keyGenerationTitle": "अपने {{selectedIntegrationName}} खाते से एपीआई कुंजी निर्माण सक्षम करें।",
    "totpButton": "प्रमाणक ऐप सेट करें",
    "totpSubtitle": "अपने <2>{{selectedIntegrationName}}</2> खाते में एक प्रमाणक ऐप जोड़ने के लिए नीचे दिए बटन पर क्लिक करें।",
    "withdrawalBody": "आपकी सुरक्षा के लिए, <1>{{selectedIntegrationName}}</1> यह आवश्यक है कि उपयोगकर्ताओं को संपत्ति निकालने के लिए ईमेल और प्रमाणीकरण ऐप MFA विधियाँ सक्षम हों",
    "withdrawalTitle": "अपने {{selectedIntegrationName}} खाते से निकासी सक्षम करें।"
  },
  "mfaSuccessPage": {
    "addAuthApp": "अपने <2>{{selectedIntegrationName}}</2> खाते में प्रमाणक ऐप जोड़ने के लिए नीचे दिए गए बटन पर क्लिक करें।",
    "emailTitle": "आपने सफलतापूर्वक अपने <2>{{selectedIntegrationName}}</2> खाते से अपना ईमेल जोड़ा है।",
    "proceed": "आगे बढ़ें",
    "proceedKey": "नीचे क्लिक करें और कुंजी बनाने के लिए आगे बढ़ें",
    "proceedTransfer": "स्थानांतरण के लिए आगे बढ़ने हेतु नीचे क्लिक करें",
    "setUpApp": "प्रमाणक ऐप सेट करें",
    "totpTitle": "आपने सफलतापूर्वक एक प्रमाणक ऐप को अपने <2>{{selectedIntegrationName}}</2> खाते से जोड़ा है।"
  },
  "mfaTitle": {
    "default": "सत्यापन कोड",
    "email": "ईमेल सत्यापन कोड",
    "phone": "एसएमएस सत्यापन कोड"
  },
  "mfaVerificationPage": {
    "checkEmail": "सबसे पहले, आपकी पहचान सत्यापित करते हैं।<1></1>कृपया, <4>{{selectedIntegrationName}}</4> से भेजे गए एक बार के सत्यापन कोड के लिए अपना ईमेल जाँचें।",
    "checkSms": "सबसे पहले, आइए आपकी पहचान सत्यापित करें।<1></1>कृपया अपने फोन में एसएमएस के माध्यम से भेजे गए एक बार के सत्यापन कोड के लिए <4>{{selectedIntegrationName}}</4> से प्राप्त संदेश की जाँच करें।",
    "confirmApp": "प्रमाणक ऐप की पुष्टि करें",
    "confirmEmail": "ईमेल की पुष्टि करें",
    "enterCode": "कृपया सत्यापन कोड दर्ज करें",
    "enterCodeFromEmail": "कृपया 6-अंकीय कोड दर्ज करें जो <2>{{selectedIntegrationName}}</2> ने<4></4>आपके ईमेल पर भेजा है।",
    "enterTotp": "कृपया अपने<1></1> प्रमाणीकरण ऐप से 6-अंकीय कोड दर्ज करें",
    "firstEnterTotp": "सबसे पहले, आपकी पहचान सत्यापित करते हैं।<1></1>\nकृपया, उस एक-बार के कोड को दर्ज करें जो आपके प्रमाणीकरण ऐप से <3>{{selectedIntegrationName}}</3> के साथ लिंक किया गया है।",
    "securityVerification": "सुरक्षा सत्यापन"
  },
  "mobileAppLink": {
    "awaitingConfirmation": "मोबाइल ऐप से पुष्टि की प्रतीक्षा की जा रही है",
    "openAppButton": "{{selectedIntegrationName}} ऐप खोलें",
    "returnToClient": "{{selectedIntegrationName}} में कनेक्शन अनुरोध को स्वीकृति देने के बाद {{clientName}} पर लौटें।",
    "sendNewRequest": "एक नया अनुरोध भेजें",
    "steps": {
      "authorize": "पुष्टि पृष्ठ पर <1> अधिकृत </1> पर क्लिक करें।",
      "openApp": "नीचे <1> {{selectedIntegrationName}} ऐप खोलें</1> पर क्लिक करें।",
      "return": "अपने खाते से लिंकिंग समाप्त करने के लिए यहाँ लौटें।"
    }
  },
  "mobileContent": {
    "actionButton": "{{integrationName}} खोलें"
  },
  "navHeader": {
    "close": "मोडल बंद करें",
    "goBack": "पीछे जाएं",
    "title": "क्रिप्टो के साथ भुगतान करें"
  },
  "networkSelectionDrawer": {
    "description": "नीचे दिए गए नेटवर्क सभी सुरक्षित और इस भुगतान के लिए अनुकूल विकल्प हैं। हमने आपके लिए सबसे कम शुल्क वाला नेटवर्क स्वतः चयनित कर लिया है।",
    "estimatedGasFeeLabel": "अनुमानित गैस शुल्क:",
    "lowestFeeLabel": "सबसे कम शुल्क",
    "title": "नेटवर्क चुनें"
  },
  "nonOAuthPermissionsPage": {
    "allow": "अनुमति दें",
    "movingFunds": "आपकी अनुमति के बिना फंड का स्थानांतरण",
    "titleWithClient": "{{clientName}} <2></2> अनुमतियाँ",
    "titleWithoutClient": "इस एप्लिकेशन की <1></1> अनुमतियाँ",
    "transactionRequest": "लेन-देन के लिए अनुरोध भेजना",
    "viewActivity": "शेष राशि, गतिविधि और प्रोफ़ाइल डेटा देखना",
    "wontAllow": "अनुमति नहीं देगा"
  },
  "oAuthBrokerPage": {
    "monitoring": "मंजूरी की प्रतीक्षा में...",
    "reopenButton": "{{selectedIntegrationName}} को फिर से खोलने के लिए यहां क्लिक करें",
    "subtitle": "अपने खाते में लॉगिन करें और अनुमति दें",
    "title": "<1></1> {{selectedIntegrationName}} विंडो पर जारी रखें"
  },
  "oauthErrorPage": {
    "description": "{{selectedIntegrationName}} अनुरोधित टोकन और/या नेटवर्क के लिए स्थानांतरण का समर्थन नहीं करता है।",
    "selectAnotherAccount": "अन्य खाता चुनें",
    "selectAnotherDescription": "जमा करने के लिए कृपया अन्य एक्सचेंज या वॉलेट का चयन करें।"
  },
  "oauthExternalPage": {
    "awaitingConnection": {
      "action": "{{selectedIntegrationName}} को फिर से खोलें",
      "subtitle": "कृपया अपने ब्राउज़र में लॉगिंग पूरा करें और एक्सेस को स्वीकृत करें।",
      "title": "कनेक्शन की प्रतीक्षा कर रहे हैं"
    },
    "checking": {
      "message": "आपकी संपत्तियाँ जाँची जा रही हैं..."
    },
    "connected": {
      "action": "{{clientName}} पर लौटें",
      "backup": "आपने सफलतापूर्वक अपने खाते को जोड़ लिया है।",
      "subtitle": "जारी रखने के लिए {{clientName}} पर वापस जाएं",
      "title": "आप {{selectedIntegrationName}} से जुड़ गए हैं"
    },
    "error": {
      "connection": {
        "action": "{{selectedIntegrationName}} को फिर से खोलें",
        "subtitle": "ऐसा लगता है कि आपने लॉग इन या एक्सेस की स्वीकृति को पूरा नहीं किया है। जारी रखने के लिए, कृपया {{selectedIntegrationName}} को फिर से खोलें और साइन-इन पूरा करें।",
        "title": "{{selectedIntegrationName}} से कनेक्ट नहीं हो सका"
      }
    },
    "redirecting": {
      "action": "{{selectedIntegrationName}} पर जारी रखें",
      "subtitle": "आपको अपने ब्राउज़र पर पुनःनिर्देशित किया जाएगा ताकि {{selectedIntegrationName}} के साथ सुरक्षित रूप से लॉग इन कर सकें। जब आपका काम पूरा हो जाएगा, तो आप स्वचालित रूप से यहाँ लौट आएंगे।",
      "title": "{{selectedIntegrationName}} पर पुनःनिर्देशित कर रहे हैं"
    }
  },
  "oauthInitialPage": {
    "continue": "{{integrationName}} पर जारी रखें",
    "description": "{{integrationName}} खोलने के लिए नीचे क्लिक करें, और भुगतान का पूर्वावलोकन करने के लिए अपने खाते में लॉग इन करें।",
    "title": "अपने खाते में लॉग इन करें"
  },
  "oAuthMessageListener": {
    "clientUsesMesh": "{{clientName}} सुरक्षित रूप से कनेक्ट करने और {{selectedIntegrationName}} में आपके स्थानांतरण की सुविधा के लिए Mesh का उपयोग करता है।",
    "description": "अपने खाते में लॉगिन करें और पहुंच की अनुमति दें",
    "monitoring": "मंजूरी की प्रतीक्षा में...",
    "open": "{{selectedIntegrationName}} खोलें",
    "reopen": "{{selectedIntegrationName}} को फिर से खोलें",
    "title": "{{selectedIntegrationName}} विंडो पर जारी रखें",
    "willFacilitate": "{{selectedIntegrationName}} के साथ सुरक्षित कनेक्शन की सुविधा प्रदान करेगा।"
  },
  "onRampLoadingScreen": {
    "approveTransferStep": {
      "client": "आप {{selectedIntegrationName}} से {{clientName}} में <1>{{amount}}</1> के स्थानांतरण को मंजूरी देते हैं।",
      "destination": "आप {{selectedIntegrationName}} से गंतव्य तक <1>{{amount}}</1> के स्थानांतरण को मंजूरी देते हैं।"
    },
    "buyingPowerPurchase": "<1>{{amount}}</1> मूल्य का {{symbol}} की खरीद <5>(~ {{amountInCrypto}})</5> में {{selectedIntegrationName}}।",
    "conversionStep": "<1>{{amount}}</1> को <3>{{currency}}</3> में रूपांतरित किया जा रहा है।",
    "depositTitle": "जमा प्रक्रिया में है",
    "description": "इसमें कुछ समय लग सकता है...",
    "existingCryptocurrencyBalance": {
      "approveClient": "आप {{selectedIntegrationName}} से {{clientName}} में स्थानांतरण को स्वीकृत करते हैं।",
      "approveDestination": "आप {{selectedIntegrationName}} से गंतव्य के लिए स्थानांतरण को स्वीकृत करते हैं।",
      "transfer": "<1>{{amount}}</1> का स्थानांतरण {{selectedIntegrationName}} से {{clientName}}।",
      "transferHideClient": "{{selectedIntegrationName}} से <1>{{amount}}</1> का स्थानांतरण।",
      "transferHideClientWithAddress": "{{selectedIntegrationName}} से {{address}} को <1>{{amount}}</1> का स्थानांतरण।",
      "transferSmartDeposit": "{{selectedIntegrationName}} से {{clientName}} के लिए एक रिले अनुबंध के माध्यम से <1>{{amount}}</1> का स्थानांतरण।",
      "transferSmartDepositHideClient": "{{selectedIntegrationName}} से रिले अनुबंध के माध्यम से <1>{{amount}}</1> का स्थानांतरण।",
      "transferSmartDepositHideClientWithAddress": "{{selectedIntegrationName}} से {{address}} को रिले अनुबंध के माध्यम से <1>{{amount}}</1> का स्थानांतरण।",
      "transferSmartDepositWithAddress": "{{selectedIntegrationName}} से {{clientName}} {{address}} को रिले अनुबंध के माध्यम से <1>{{amount}}</1> का स्थानांतरण।",
      "transferWithAddress": "{{selectedIntegrationName}} से {{clientName}} {{address}} को <1>{{amount}}</1> का स्थानांतरण।"
    },
    "mayTakeFewSeconds": "इसमें कुछ सेकंड लग सकते हैं",
    "onrampTitle": "खरीदारी प्रगति में है",
    "paymentMethodDepositUsage": "{{paymentMethod}} से {{selectedIntegrationName}} तक <1>{{amount}}</1> का जमा।",
    "paymentTitle": "भुगतान प्रगति में है",
    "processing": "भुगतान संसाधित किया जा रहा है",
    "transactionTitle": "लेन-देन प्रगति में है",
    "tryAgain": "पुनः प्रयास करें"
  },
  "orderSummaryDrawer": {
    "merchantInfoName": "व्यापारी: {{clientName}}",
    "title": "ऑर्डर सारांश",
    "totalLabel": "कुल"
  },
  "passwordPage": {
    "fieldError": "कृपया अपना {{field}} दर्ज करें",
    "fieldErrorWithIntegration": "कृपया अपना {{integrationName}} {{field}} दर्ज करें",
    "forgotPassword": "पासवर्ड भूल गए",
    "tabs": {
      "email": "ईमेल",
      "mobileApp": "मोबाइल ऐप",
      "phone": "फ़ोन",
      "qrCode": "क्यूआर कोड"
    },
    "title": "लॉग इन करें"
  },
  "paymentMethods": {
    "bankAccount": "बैंक खाता",
    "card": "डेबिट कार्ड",
    "default": "लिंक्ड भुगतान विधि",
    "digitalWallet": "डिजिटल वॉलेट"
  },
  "paymentUpdateDrawerContent": {
    "cancel": "रद्द करें",
    "clickToPay": "इस भुगतान को करने के लिए अपनी {{token}} शेष राशि बढ़ाने हेतु नीचे क्लिक करें।",
    "description": "खरीद के बाद आपकी {{token}} शेष राशि, {{token}} की कीमत में बदलाव और/या गैस शुल्क के कारण अपेक्षा से कम है।",
    "ifDontComplete": "यदि आप भुगतान नहीं करते हैं, तो आपका {{token}} शेष आपके {{selectedIntegrationName}} खाते में रहेगा।",
    "onYourAccount": "आपके खाते पर",
    "title": "भुगतान अपडेट",
    "topUp": "{{token}} शेष राशि टॉप अप करें"
  },
  "payPalConnectOAuthPage": {
    "close": "बंद करें",
    "continue": "{{selectedIntegrationName}} पर जारी रखें",
    "enterAmount": "स्थानांतरण राशि दर्ज करें",
    "notSupported": "{{selectedIntegrationName}} अनुरोधित टोकन और/या नेटवर्क के लिए स्थानांतरण को समर्थन नहीं करता है।",
    "selectAnotherAccount": "अन्य खाता चुनें",
    "selectAnotherExchange": "जमा करने के लिए कृपया अन्य एक्सचेंज या वॉलेट का चयन करें।",
    "selectNetwork": "स्थानांतरण नेटवर्क चुनें",
    "title": "स्थानांतरण के लिए संपत्ति चुनें"
  },
  "previewPageUI": {
    "accountLabel": "खाता",
    "buildingPreviewPayment": "आपके भुगतान पूर्वावलोकन का निर्माण हो रहा है...",
    "confirmTransaction": "अपने {{selectedIntegrationName}} ऐप में इस लेन-देन की पुष्टि करें।",
    "fewSeconds": "इसमें कुछ सेकंड लग सकते हैं",
    "includeFeesMessage": "शुल्क में {{amount}} शामिल है",
    "networkLabel": "नेटवर्क",
    "paymentTitle": "{{clientName}} को भुगतान करें",
    "paymentTotalLabel": "कुल भुगतान करें",
    "payWithLabel": "इसके साथ भुगतान करें",
    "payWithLabelWithName": "{{integrationName}} के साथ भुगतान करें",
    "processingPayment": "आपका भुगतान संसाधित हो रहा है"
  },
  "previewTransfer": {
    "allFeesIncluded": "सभी शुल्क शामिल हैं",
    "amountWithFiat": "{{cryptoAmount}} ~{{fiatAmount}}",
    "approveTransferRequest": "अपने वॉलेट में ट्रांसफर अनुरोध<1></1> को स्वीकृति दें",
    "changeAmount": "राशि बदलें",
    "depositTitle": "जमा पूर्वावलोकन",
    "dustLeft": "आपके पास कुछ {{symbol}} धूल शेष हो सकती है।",
    "estimatedGasFee": "अनुमानित गैस शुल्क",
    "estimatedGasFeeHint": "इस लेन-देन को संसाधित करने के लिए नेटवर्क मान्यकर्ताओं को उनके उपयोग की गई कंप्यूटिंग शक्ति की क्षतिपूर्ति करने के लिए भुगतान की जाने वाली अनुमानित शुल्क।",
    "from": "से",
    "fundingWith": "साथ वित्तपोषण",
    "institutionTransferFee": "{{selectedIntegrationName}} निकासी शुल्क",
    "institutionTransferFeeHint": "फीस जो {{selectedIntegrationName}} आपके {{symbol}} से बाहर स्थानांतरण को सुविधाजनक बनाने के लिए वसूल करेगा।",
    "insufficientFunds": "अपर्याप्त धनराशि",
    "maxAmount": "आपका खाता अधिकतम <2>{{networkMaxAmount}}</2> तक वित्त पोषण कर सकता है। आप अपना स्थानांतरण इस राशि पर समायोजित करना चाहेंगे?",
    "monitoring": "मंजूरी की प्रतीक्षा में...",
    "network": "नेटवर्क",
    "onrampTitle": "खरीद पूर्वावलोकन",
    "payingWith": "इसके साथ भुगतान",
    "paymentTitle": "भुगतान का पूर्वावलोकन",
    "proceed": "आगे बढ़ें",
    "processingFee": "प्रसंस्करण शुल्क",
    "processingFeeHint": "इस लेन-देन को संसाधित करने के लिए एकत्र किया गया शुल्क।",
    "receive": "प्राप्त करें",
    "resendTransferRequest": "स्थानांतरण अनुरोध दोबारा भेजें",
    "seconds": "{{seconds}}से",
    "symbolBalance": "{{symbol}} शेष राशि",
    "to": "को",
    "total": "कुल",
    "transferDeclined": "स्थानांतरण अस्वीकार किया गया",
    "transferDeclinedBody": "आपने अपने वॉलेट में स्थानांतरण अनुरोध को अस्वीकार कर दिया है।",
    "transferTitle": "स्थानांतरण का पूर्वावलोकन",
    "youMayReceiveLess": "{{symbol}} की कीमत में उतार-चढ़ाव के कारण आपको कम राशि प्राप्त हो सकती है।"
  },
  "privacyComponent": {
    "content": "आपका डेटा हर समय निजी और एन्क्रिप्टेड रहता है।"
  },
  "qrCodePassword": {
    "expired": "क्यूआर कोड की समय सीमा समाप्त हो गई है",
    "generateNew": "एक नया क्यूआर कोड उत्पन्न करें",
    "qrCodeLabel": "आपके मोबाइल उपकरण पर कनेक्शन स्थापित करने के लिए क्यूआर कोड स्कैन किया जा सकता है।",
    "scanText": "तुरंत लॉग इन करने के लिए अपने {{appName}} ऐप <1></1> के साथ इस कोड को स्कैन करें।"
  },
  "receiveAmountInput": {
    "onNetwork": "{{network}} पर"
  },
  "revolutConnectOAuthPage": {
    "amountMustBeAtLeast": "राशि कम से कम $8 होनी चाहिए।",
    "continue": "{{selectedIntegrationName}} पर जारी रखें",
    "enterAmount": "स्थानांतरण राशि दर्ज करें",
    "selectAsset": "स्थानांतरण के लिए संपत्ति चुनें",
    "selectNetwork": "स्थानांतरण नेटवर्क का चयन करें"
  },
  "robinhoodConnectOAuthPage": {
    "continue": "{{selectedIntegrationName}} पर जारी रखें",
    "enterAmount": "स्थानांतरण राशि दर्ज करें",
    "selectAsset": "स्थानांतरण के लिए संपत्ति चुनें",
    "selectNetwork": "स्थानांतरण नेटवर्क का चयन करें"
  },
  "selectCryptoFundingPage": {
    "title": "संपत्ति चुनें"
  },
  "selectHoldingPage": {
    "binanceDirectNoAssetsBody1": "ऐसा लगता है कि आपके जुड़े खाते में कोई संपत्ति नहीं है।",
    "binanceDirectNoAssetsBody2": "आप अपने खाते में फंड जोड़ सकते हैं या इस स्थानांतरण के लिए एक अलग खाता कनेक्ट कर सकते हैं।",
    "cannotFundBody": "इस खाते में इस लेनदेन को पूरा करने के लिए आपके पास पर्याप्त क्रिप्टो या फिएट बैलेंस नहीं है।",
    "cannotFundTitle": "लेनदेन को निधि प्रदान नहीं की जा सकती",
    "connectAnotherButton": "अन्य खाता कनेक्ट करें",
    "defaultTitle": "टोकन चुनें",
    "depositTitle": "जमा टोकन चुनें",
    "ineligibleAssets": "अयोग्य संपत्तियाँ",
    "loading": "आपकी संपत्तियाँ लोड हो रही हैं...",
    "noAssetsTitle": "लिंक किए गए खाते में कोई संपत्ति नहीं पाई गई",
    "noEligibleAssetsTitle": "इस खाते में कोई भी संपत्ति इस स्थानांतरण के लिए योग्य नहीं है",
    "notEnoughtBody": "अपने खाते में और {{symbol}} जोड़ें, फिर यहाँ वापस आकर पुनः प्रयास करें।",
    "notEnoughtTitle": "पर्याप्त {{symbol}} नहीं",
    "otherEligible": "अन्य योग्य संपत्तियाँ",
    "paymentTitle": "भुगतान टोकन चुनें",
    "returnToAppButton": "एप्लिकेशन पर वापस जाएं",
    "returnToClientButton": "{{clientName}} पर लौटें",
    "spotAccountsBody": "वर्तमान में केवल स्पॉट खाते समर्थित हैं। मार्जिन जैसे अन्य खाते प्रकार में संपत्तियां दिखाई नहीं देंगी।",
    "topUpButton": "बैलेंस टॉप अप करें",
    "topUpUSDCInstruction": "अपने Phantom वॉलेट में USDC बैलेंस टॉप अप करें।",
    "tryAgainFromTaoInstruction": "कृपया अपने TAO चेकआउट पेज से दोबारा प्रयास करें।",
    "unableTransferError": "स्थानांतरण आरंभ नहीं किया जा सका।"
  },
  "selectItem": {
    "label": "{{text}} चुनें"
  },
  "selectNetworkPage": {
    "ineligibleNetwork": "अयोग्य नेटवर्क"
  },
  "selectNetworkScreen": {
    "title": "कनेक्ट करने के लिए नेटवर्क चुनें"
  },
  "selectWalletScreen": {
    "ledgerDevice": "लेज़र डिवाइस",
    "ledgerLiveMobileApp": "लेज़र लाइव मोबाइल ऐप",
    "title": "आप कैसे {{selectedIntegrationName}} से कनेक्ट करना चाहेंगे?"
  },
  "sessionExpired": {
    "title": "आपका सत्र समाप्त हो गया है।"
  },
  "sessionInfo": {
    "text": "यदि आपके कोई प्रश्न हैं, कृपया इसे सत्र आईडी <2>{{sessionId}}</2> के साथ रिपोर्ट करें।"
  },
  "setupAuthAppPage": {
    "alternativeText": "इसके विकल्प के रूप में, आप इस मैनुअल कोड को प्रमाणिकरण ऐप में पेस्ट कर सकते हैं",
    "copyCodeTitle": "मैनुअल कोड",
    "downloadStep": "Google Play या App Store से <1>Google Authenticator ऐप</1> डाउनलोड करें",
    "nextButton": "अगला",
    "qrCodeAlt": "क्यूआर कोड",
    "scanStep": "<1> क्यूआर कोड स्कैन करके</1>अपने प्रमाणक ऐप में {{selectedIntegrationName}} जोड़ें",
    "title": "प्रमाणक ऐप सेट करें"
  },
  "setupEmailPage": {
    "description": "अपना ईमेल पता दर्ज करें।<1></1><2>{{selectedIntegrationName}}</2> आपके खाते में कुछ क्रियाओं को निष्पादित करते समय आपको पुष्टिकरण कोड भेजने के लिए इस ईमेल का उपयोग करेगा।",
    "emailTitle": "ईमेल",
    "enterError": "कृपया ईमेल दर्ज करें",
    "title": "ईमेल सेट करें"
  },
  "termsAndConditionsPage": {
    "paragraph1": "Mesh Connect, Inc. (<1>“कंपनी”</1>) एक तकनीकी प्रदाता है जो एक संचार उपकरण (<3>“उपकरण”</3>) बनाता है, जो उस तृतीय-पक्ष सेवा (<5>“एंड यूज़र सेवा”</5>) की कुछ कार्यक्षमताओं को सक्षम करने में मदद करता है जिसे आप उपयोग कर रहे हैं। यह कार्यक्षमता आपको एंड यूज़र सेवा के माध्यम से अपने तृतीय-पक्ष खातों और वॉलेट्स (<7>“कनेक्टेड अकाउंट्स”</7>) के साथ संवाद करने में सक्षम बनाती है, जिसमें वे निर्देश भेजना शामिल है जिन्हें आप निष्पादित करना चाहते हैं।",
    "paragraph10": "सुलह का प्रबंध अमरीकी सुलह संघ द्वारा इसके उपभोक्ता सुलह नियमों के तहत किया जायेगा, जो इन शर्तों द्वारा संशोधित हैं। उपभोक्ता सुलह नियम ऑनलाइन उपलब्ध हैं <2>https://www.adr.org/sites/default/files/Consumer%20Rules.pdf</2> पर। सुलहकर्ता, यदि किसी सुनवाई की आवश्यकता होती है, तो टेली काॅन्फ्रेंस या वीडियो काॅन्फ्रेंस के माध्यम से सुनवाई करेगा, व्यक्तिगत उपस्थिति के बजाय, जब तक कि सुलहकर्ता आपकी या हमारी अनुरोध पर नहीं मानता कि व्यक्तिगत सुनवाई उपयुक्त है। कोई भी व्यक्तिगत उपस्थिति ऐसी जगह पर होगी, जो दोनों पक्षों के लिए यात्रा और अन्य महत्वपूर्ण परिस्थितियों को ध्यान में रखते हुए उचित रूप से सुविधाजनक हो। यदि आप और कंपनी स्थान के बारे में सहमत नहीं हो सकते, तो ये निर्णय एएए या सुलहकर्ता द्वारा किया जाना चाहिए। सुलहकर्ता का निर्णय इन शर्तों का पालन करेगा और अंतिम और बाध्यकारी होगा। सुलहकर्ता के पास अस्थायी, अंतरिम या स्थायी प्रतिबंधात्मक राहत प्रदान करने या इन शर्तों का विशेष प्रदर्शन करने के लिए आदेश देने का अधिकार होगा, लेकिन केवल उस हद तक ज़रूरी है जितनी हद तक सुलहकर्ता के सामने व्यक्तिगत दावे द्वारा राहत दिया जाता है। सुलहकर्ता द्वारा दी गई अवार्ड को किसी भी न्यायालय में पुष्टि और आरोपित किया जा सकता है। उपरोक्त किसी भी चीज के बावजूद, इन शर्तों में कुछ भी आपको संघीय, राज्य या स्थानीय एजेंसियों को मुद्दों के ध्यान में लाने से नहीं रोकेगा और, यदि कानून इसकी अनुमति देता है, तो वे आपके लिए हमें राहत दिलाने का प्रयास कर सकते हैं।",
    "paragraph11": "ये शर्तें आपके और कंपनी के बीच उनके विषय से संबंधित पूर्ण समझौता बनाते हैं, और इन मामालों पर सभी पूर्व के प्रतिनिधानियों या समझौतों, चाहे मौखिक या लिखित हों, को खत्म करते हैं। यदि कोई शर्त लागू कानून के तहत अमान्य है, तो वह शर्त यहां कानून से अनुकूलित की जाती है, जबकि मूल शर्त की मंशा को अधिकतम रूप से संरक्षण प्रदान करते हुए। कोई भी शर्त जो कि इस प्रकार से संशोधित नहीं की जा सकती है, उसे अलग किया जाएगा और सभी बाकी शर्तें प्रभाव में रहेंगी। आप मान्यता देते हैं और सहमत होते हैं कि कंपनी के सेवा प्रदाता इन शर्तों के अंशधारी अतिरिक्त लाभार्थी बनाए जाते हैं। इन शर्तों और शर्तों को स्वीकार करके या टूल का उपयोग करके, आप इस समझौते की शर्तों और शर्तों से बाधित होने के लिए सहमत होते हैं।",
    "paragraph2": "आप मान्य करते हैं और सहमत होते हैं कि एन्ड यूज़र सर्विस की कुछ कार्यक्षमता टूल पर आधार रखती है; कि इस तरह की कार्यक्षमता का आपका उपयोग आपके निर्देश के अनुसार है; कि न तो कंपनी और न ही इसके सेवा प्रदाता ब्रोकरेज सेवाएं उपलब्ध कराते हैं या भुगतान प्रसंस्करण में संलग्न होते हैं; और कि न तो कंपनी और न ही इसके सेवा प्रदाता के पास एन्ड यूज़र सर्विस या किसी कनेक्टेड अकाउंट के लिए कोई ज़िम्मेदारी या दायित्व होता है, या उनके प्रदाताओं की शर्तें, नीतियाँ, कार्य या चूक।",
    "paragraph3": "आप प्रमाणित करते हैं और विश्वास जताते हैं कि आपके पास सभी अधिकार और सहमतियां हैं जो प्रत्येक कनेक्टेड अकाउंट में जोड़ने या वहां पहुंच के लिए आवश्यक हैं, जिसमें कंपनी और उसके सेवा प्रदाताओं को आपके अकाउंट लॉगिन जानकारी, वॉलेट पते और/या आपके अकाउंट या व्यक्तिगत जानकारी देने का अधिकार शामिल है प्रत्येक कनेक्टेड अकाउंट के लिए। आप यहां कंपनी और उसके सेवा प्रदाताओं को निर्देशों के अलावा जानकारी, डाटा और अन्य सामग्रियां एन्ड यूज़र सर्विस और प्रत्येक कनेक्टेड अकाउंट के बीच भेजने के लिए अधिकृत करते हैं, और आप इसे स्वीकार करते हैं कि कंपनी और उसके सेवा प्रदाताओं के पास इन निर्देशों की निष्पादन या सामग्री (उनकी सटीकता, समयबद्धता या सम्पूर्णता सहित) के लिए कोई ज़िम्मेदारी या दायित्व नहीं है।",
    "paragraph4": "आप यह स्वीकार करते हैं कि आपने कंपनी की गोपनीयता नीति पढ़ ली है, जो <2>https://meshconnect.com/privacy-policy</2> पर उपलब्ध है, और सहमत हैं कि, टूल का उपयोग करके, आप गोपनीयता नीति में निर्धारित और वर्णित आपकी व्यक्तिगत जानकारी के कंपनी के उपयोग को अनुकूलित करते हैं।",
    "paragraph5": "टूल \"जैसा है\" और \"जैसे उपलब्ध हो\" के आधार पर सभी कमियों के साथ उपलब्ध कराया जाता है और बिना किसी प्रतिनिधित्व या किन्हीं प्रकार की गारंटी के। कंपनी टूल के संबंध में कोई भी अभिव्यक्ति या घोषणाएं नहीं करती है, चाहे व्यक्त या निहित हो, जिसमें कोई वाणिज्यिक उपयुक्तता, किसी विशेष उद्देश्य के फिटनेस या अनाचरण का कोई दायित्व शामिल नहीं है।",
    "paragraph6": "किसी भी स्थिति के अंतर्गत न तो कंपनी और न ही उसके सेवा प्रदाता, संपर्क, गारंटी, अपराध (अन्याय सहित), उत्पाद दायित्व, कठोर दायित्व या अन्य किसी सिद्धांत के तहत किसी अप्रत्यक्ष, आकस्मिक, विशेष या परिणामस्वरूप हानि के लिए उपकरण, एन्ड यूज़र सेवा या किसी भी कनेक्टेड अकाउंट का उपयोग (या उपयोग के अक्षम) के संबंध में, इन निर्देशों या सामग्रियों सहित जो उपकरण द्वारा सक्षम कार्यक्षमता का उपयोग कर प्रेषित की गई हैं। उपरोक्त सीमाएं, बहिष्करण और अस्वीकरण अधिकतम सीमा में लागू कानून के तहत लागू होंगी, भले ही कोई भी उपाय अपनी मूल उद्देश्य में असफल हो। उपरोक्त के बिना सीमाएं रखते हुए, कंपनी और उसके सेवा प्रदाताओं का उपकरण के संबंध में सामूहिक दायित्व दस डॉलर से अधिक नहीं होगा।",
    "paragraph7": "आप कंपनी और उसके निदेशकों, अधिकारियों, कर्मचारियों, लाइसेंसदाताओं, ठेकेदारों और प्रतिनिधियों को किसी भी तीसरे-पक्षीय दावों, कार्यों, मुकदमों, जांचों या कार्यवाही से, और किसी भी नुकसान, जिम्मेवारियों, हानियाँ, लागतों और उपकरण का उपयोग (या दुरुपयोग) से उत्पन्न या संलग्न खाती हो, एन्ड यूज़र सेवा और/या किसी भी कनेक्टेड अकाउंट के खिलाफ सुरक्षित रखेंगे।",
    "paragraph8": "कंपनी इन शर्तों को कभी भी बदल सकती है। किसी भी ऐसे बदलाव के बाद आप उपकरण द्वारा सक्षम की गई किसी भी कार्यक्षमता का जारी उपयोग आपके द्वारा अपडेट की गई शर्तों की स्वीकृति को प्रकट करता है।",
    "paragraph9": "इन शर्तों का संचालन डेलावेयर राज्य के कानूनों के अधीन होगा, इसके कानूनी सिद्धांत विकल्पों को छोड़कर। लघु दावा न्यायालय के लिए योग्य विवादों को छोड़कर, इन शर्तों से उत्पन्न या संबंधित सभी विवादों के नियम, चाहे अनुबंध, अपराध, कानून, धोखाधड़ी, गलत प्रतिनिधित्व या किन्हीं अन्य कानूनी सिद्धांत के आधार पर हों, एक मध्यस्थ तटस्थ के सामने अंतिम और बाध्यकारी मध्यस्थता के माध्यम से सुलझाया जाएगा बजाय अदालत द्वारा जज या जूरी के और आप सहमति देते हैं कि कंपनी और आप दोनों किसी जूरी द्वारा सुनवाई का अधिकार छोड़ रहे हैं। ऐसे विवादों में, विवादों का अर्थ और अनुवाद शामिल है, जबकि उनकी वैधता, फूटकारिता या किसी भी खंड का एक खंड का उल्लंघन, रद्द करने की क्षमता या वैधता शामिल होगी। सभी ऐसे मामलों पर मध्यस्थ द्वारा निर्णय लिया जाएगा और अदालत या जज द्वारा नहीं। आप सहमत हैं कि इन शर्तों के तहत कोई भी मध्यस्थता एक व्यक्ति के आधार पर होगी; वर्गीय मध्यस्थ और वर्गीय क्रियाओं की अनुमति नहीं है, और आप वर्गीय कारवाई में भाग लेने की क्षमता को छोड़ने के लिए सहमत हैं।",
    "title": "{{shortName}} अंतिम उपयोगकर्ता<2></2>शर्तें और नियम"
  },
  "transferAmountPage": {
    "buttonTitle": {
      "deposit": "जमा पूर्वावलोकन",
      "onramp": "खरीद पूर्वावलोकन",
      "transfer": "हस्तांतरण पूर्वावलोकन"
    },
    "errorMessage": {
      "insufficientFunds": "हस्तांतरण और गैस शुल्क को कवर करने के लिए अपर्याप्त धनराशि। अधिकतम हस्तांतरण राशि {{maxAmount}} है।",
      "minimumAmount": "न्यूनतम हस्तांतरण राशि {{minAmount}} है।",
      "zeroAmount": "कृपया गैर-शून्य राशि दर्ज करें"
    },
    "title": {
      "deposit": "जमा राशि दर्ज करें",
      "onramp": "खरीद राशि दर्ज करें",
      "transfer": "स्थानांतरण राशि दर्ज करें"
    }
  },
  "transferCanceledPage": {
    "title": "स्थानांतरण रद्द किया गया है",
    "titlePayment": "भुगतान रद्द कर दिया गया है",
    "willRemain": "आपके {{integrationName}} खाते में बना रहेगा।",
    "yourBalance": "आपका शेष {{token}}"
  },
  "transferDeviceConfirmation": {
    "awaitingConfirmation": "मोबाइल ऐप से पुष्टि की प्रतीक्षा कर रहे हैं",
    "confirmButton": "मैंने अपने ऐप पर सत्यापित कर दिया है",
    "description": "अपने {{selectedIntegrationName}} मोबाइल ऐप में पुष्टि करें कि यह वास्तव में आप हैं जो लॉग इन करने का प्रयास कर रहे हैं।",
    "desktopSteps": {
      "confirm": "यह सुनिश्चित करने के लिए प्रेरणा पर पुष्टि करें कि यह आप ही हैं",
      "openApp": "अपने फ़ोन पर {{selectedIntegrationName}} ऐप खोलें",
      "return": "जारी रखने के लिए यहाँ लौटें"
    },
    "mobileSteps": {
      "clickOpen": "नीचे <1> {{selectedIntegrationName}} ऐप खोलें</1> पर क्लिक करें",
      "verifyLogin": "पुष्टि करें कि आप नए डिवाइस से लॉग इन कर रहे हैं।",
      "verifyTransfer": "पुष्टि करें कि आप ही स्थानांतरण का अनुरोध कर रहे हैं।"
    },
    "openApp": "{{selectedIntegrationName}} ऐप खोलें",
    "sendNewRequest": "एक नया अनुरोध भेजें",
    "title": "सत्यापन",
    "tryAnother": "दूसरे तरीका आज़माएं"
  },
  "transferEmailApprovalConfirmation": {
    "approve": "पुष्टिकरण पृष्ठ पर <1>स्वीकृत करें</1> पर क्लिक करें।",
    "approveOrCancel": "ईमेल में <1>स्वीकृत करें या निकासी रद्द करें</1> पर क्लिक करें।",
    "confirmButton": "मैंने निकासी को स्वीकृत किया है।",
    "description": "कृपया अपने इनबॉक्स में एक ईमेल देखें जिसमें नई निकासी की पुष्टि करने के लिए कहा गया है।",
    "return": "यहां लौटें और अपनी ट्रांसफर को जारी रखने के लिए नीचे क्लिक करें।",
    "title": "निकासी स्वीकृत करें"
  },
  "transferErrorPage": {
    "defaultError": "एक अज्ञात त्रुटि हुई है। कृपया एक नई स्थानांतरण सत्र शुरू करने के लिए नीचे क्लिक करें।"
  },
  "transferErrors": {
    "failedToExecute": "हस्तांतरण निष्पादित करने में विफल",
    "failedToPreview": "हस्तांतरण पूर्वावलोकन में विफल",
    "mfaEmailFailed": "ईमेल से गलत कोड, कृपया कोड फिर से दर्ज करें",
    "mfaFaceFailed": "सत्यापन विफल, कृपया पुनः प्रयास करें",
    "mfaFailed": "गलत कोड, कृपया कोड फिर से दर्ज करें",
    "mfaPhoneFailed": "गलत एसएमएस कोड, कृपया कोड पुनः दर्ज करें",
    "mfaTotpFailed": "गलत TOTP कोड, कृपया कोड फिर से दर्ज करें",
    "mfaTradingPinFailed": "MFA ट्रेडिंग पिन विफल, कृपया कोड फिर से दर्ज करें"
  },
  "transferFacePage": {
    "clickOpenApp": "<1>{{selectedIntegrationName}} ऐप खोलें</1> पर क्लिक करें ताकि आपका ऐप खुल जाए और चेहरा सत्यापन पूरा हो सके।",
    "completeMobile": "चेहरा सत्यापन पूरा करें ताकि यह पुष्टि हो सके कि वास्तव में आप ही धनराशि स्थानांतरित करने का प्रयास कर रहे हैं।",
    "confirmCompleted": "मैंने सत्यापन पूरा कर लिया है",
    "openApp": "{{selectedIntegrationName}} ऐप खोलें",
    "reopenApp": "{{selectedIntegrationName}} ऐप को पुनः खोलें",
    "return": "फिर अपने खाते को लिंक करने के लिए यहाँ लौटें।",
    "returnContinue": "अपने खाते को लिंक करने के लिए यहाँ लौटें।",
    "scanQR": "क्यूआर कोड स्कैन करें ताकि चेहरा सत्यापन पूरा हो सके और यह पुष्टि हो कि वास्तव में आप ही धनराशि स्थानांतरित करने का प्रयास कर रहे हैं।",
    "title": "सत्यापन"
  },
  "transferMfaPage": {
    "title": "सत्यापन",
    "verify": "सत्यापित करें"
  },
  "transferPreviewErrorPage": {
    "aboveMaximum": "{{integrationName}} अधिकतम सीमा से ऊपर",
    "belowMinimum": "{{integrationName}} न्यूनतम सीमा से नीचे",
    "connectAnotherAccount": "कृपया एक और अकाउंट कनेक्ट करें।",
    "connectDifferent": "किसी भिन्न खाते को कनेक्ट करें",
    "insufficientBalanceError": "इस लेन-देन के लिए अपर्याप्त शेष राशि है।",
    "insufficientFunds": "अपर्याप्त कोष",
    "unknownError": "एक अज्ञात त्रुटि हुई है। कृपया एक नई स्थानांतरण सत्र शुरू करने के लिए नीचे क्लिक करें।"
  },
  "transferSteps": {
    "approveTransfer": "आप {{integrationName}} से {{clientName}} में स्थानांतरण को स्वीकृति देते हैं।",
    "approveTransferDeFi": "आपको {{integrationName}} में स्थानांतरण को स्वीकृत करने की आवश्यकता होगी।",
    "approveTransferToDestination": "आप {{integrationName}} से गंतव्य स्थान पर स्थानांतरण को स्वीकृति देते हैं।",
    "convertAmount": "{{fromAmount}} का {{toCurrency}} में रूपांतरण",
    "depositAmount": "{{paymentMethod}} से {{integrationName}} में {{amount}} का जमा",
    "purchaseAmount": "{{integrationName}} में {{cryptocurrencySymbol}} की <2>{{amount}}</2> की खरीदारी।",
    "showLess": "कम दिखाएँ",
    "showMore": "अधिक दिखाएँ",
    "title": "क्या होगा",
    "transferAmount": "<1>{{cryptoAmount}}</1> का हस्तांतरण {{integrationName}} से {{clientName}} {{targetAddress}}।",
    "transferAmountSmartDeposit": "<1>{{cryptoAmount}}</1> का हस्तांतरण {{integrationName}} से {{clientName}} {{targetAddress}} रिले कॉन्ट्रैक्ट के माध्यम से।"
  },
  "transferUpdateDrawerContent": {
    "approveTransfer": "हस्तांतरण को स्वीकृत करें",
    "cancel": "रद्द करें",
    "description": "{{token}} कीमत और/या गैस फीस में बदलाव के कारण खरीदी गई राशि अपेक्षित से कम है।",
    "ifDontComplete": "यदि आप हस्तांतरण पूरा नहीं करते हैं, तो आपका {{token}} बैलेंस आपके {{selectedIntegrationName}} खाते में रहेगा।",
    "onYourAccount": "आपके खाते पर",
    "title": "हस्तांतरण अद्यतन",
    "youWillReceive": "आप प्राप्त करेंगे"
  },
  "transferWithdrawalAddressConfirmation": {
    "checkInbox": "कृपया अपने इनबॉक्स की जाँच करें क्योंकि आपको एक नए निकासी पते की पुष्टि के लिए एक ईमेल भेजा गया है।",
    "clickConfirm": "ईमेल में <1>पते की पुष्टि करें</1> पर क्लिक करें।",
    "confirmedButton": "मैंने पते की पुष्टि की है",
    "return": "यहां लौटें और हस्तांतरण को पूरा करने के लिए नीचे क्लिक करें।",
    "title": "निकासी पते की पुष्टि करें"
  },
  "trezorContext": {
    "failedGetBTCError": "BTC वॉलेट जानकारी प्राप्त करने में विफल",
    "failedGetETHError": "ETH पता प्राप्त करने में विफल",
    "failedSignBTCError": "BTC संदेश पर हस्ताक्षर करने में विफल",
    "failedSignETHError": "ETH संदेश पर हस्ताक्षर करने में विफल",
    "unknownError": "अज्ञात त्रुटि हुई"
  },
  "trezorDeviceConnected": {
    "clientVerifyLabel": "{{clientName}} को आपका वॉलेट सत्यापित करना होगा",
    "secureLabel": "तेज़, सुरक्षित और मुफ्त",
    "secureText": "हस्ताक्षर करने से {{clientName}} को आपके वॉलेट के साथ कोई लेन-देन करने की अनुमति नहीं मिलती है।",
    "signText": "आपको अपने Trezor डिवाइस में एक संदेश पर हस्ताक्षर करने के लिए संकेत दिया जाएगा जो पुष्टि करता है कि आप इस वॉलेट के मालिक हैं।",
    "title": "लगभग हो चुका है!",
    "verifyingLabel": "आपके वॉलेट का सत्यापन हो रहा है..."
  },
  "trezorError": {
    "connectionDeclinedBody": "आपने अपनी वॉलेट से कनेक्ट करने के अनुरोध को अस्वीकृत कर दिया है, या एक पिछला अनुरोध अभी भी सक्रिय है।",
    "connectionDeclinedTitle": "कनेक्शन अस्वीकृत",
    "signatureDeclinedBody": "आपने अपने वॉलेट में हस्ताक्षर अनुरोध को अस्वीकार कर दिया है, या पिछला अनुरोध अभी भी सक्रिय है।",
    "signatureDeclinedTitle": "हस्ताक्षर अस्वीकार कर दिया गया"
  },
  "trezorInitial": {
    "clientVerifyLabel": "{{clientName}} को आपका वॉलेट सत्यापित करना होगा",
    "clientVerifyText": "आपको सुरक्षित रूप से अपने Trezor में ट्रांसफर किया जाएगा, ताकि आप अपने डिवाइस में एक संदेश पर हस्ताक्षर कर सकें, जो आपकी वॉलेट का स्वामित्व पुष्ट करे।",
    "connectingLabel": "आपके वॉलेट को जोड़ने की प्रक्रिया चल रही है...",
    "secureLabel": "तेज़, सुरक्षित और मुफ्त",
    "secureText": "हस्ताक्षर करने से किसी भी तरह से {{clientName}} को आपके वॉलेट के साथ लेन-देन करने की अनुमति नहीं मिलती है।"
  },
  "verifyAddressAndNetworkErrorPage": {
    "body": "{{clientName}} आपसे <3>{{requestedNetworkName}}</3> पते <6>{{truncatedRequestedAddress}}</6> का स्वामित्व सत्यापित करने का अनुरोध कर रहा है। यह पता जुड़े हुए वॉलेट से संबद्ध नहीं है। कृपया कोई अन्य वॉलेट कनेक्ट करें।",
    "connectAnotherAction": "अन्य वॉलेट कनेक्ट करें",
    "title": "ओह हो!"
  },
  "verifyError": {
    "body": "आपके हार्डवेयर वॉलेट को सत्यापित नहीं किया जा सका। कृपया सुनिश्चित करें कि आपने सही नेटवर्क चुना है और सही वॉलेट का पता दर्ज किया है।",
    "title": "सत्यापन विफल"
  },
  "verifyErrorPage": {
    "body": "आपने अपने वॉलेट में हस्ताक्षर अनुरोध अस्वीकार कर दिया है, या पिछला अनुरोध अभी भी सक्रिय है। {{clientName}} आपके वॉलेट के स्वामित्व को बिना हस्ताक्षर के सत्यापित नहीं कर सकता।",
    "title": "सत्यापन अस्वीकृत"
  },
  "wallectConnect": {
    "noActiveSessionError": "कोई सक्रिय WalletConnect सत्र नहीं है",
    "transactionHashError": "लेन-देन हैश प्राप्त नहीं हो सका",
    "unknownError": "एक अज्ञात त्रुटि हुई। {{error}}"
  },
  "walletDoneScreen": {
    "completePaymentMessage": "{{clientName}} खरीदारी पूरी करने के लिए अपने चेकआउट अनुभव पर लौटें।",
    "continueMessage": "कृपया अपने {{clientName}} ऐप में जारी रखें।",
    "successMessage": "आपने अपने {{walletName}} वॉलेट का स्वामित्व सफलतापूर्वक सत्यापित कर लिया है।"
  },
  "withdrawalLockedErrorPage": {
    "another": "दूसरे खाते से स्थानांतरण करें",
    "title": "निकासी अस्थायी रूप से निष्क्रिय हैं"
  }
}
